[{"都道府県コード":"16","都道府県名":"富山県","都道府県名カナ":"トヤマケン","都道府県名ローマ字":"TOYAMA KEN","市区町村コード":"16211","市区町村名":"射水市","市区町村名カナ":"イミズシ","市区町村名ローマ字":"IMIZU SHI","大字町丁目コード":"162110001000","大字町丁目名":"青井谷","緯度":36.676826,"経度":137.066661},{"都道府県コード":"16","都道府県名":"富山県","都道府県名カナ":"トヤマケン","都道府県名ローマ字":"TOYAMA KEN","市区町村コード":"16211","市区町村名":"射水市","市区町村名カナ":"イミズシ","市区町村名ローマ字":"IMIZU SHI","大字町丁目コード":"162110002001","大字町丁目名":"あおば台一丁目","緯度":36.718116,"経度":137.052174},{"都道府県コード":"16","都道府県名":"富山県","都道府県名カナ":"トヤマケン","都道府県名ローマ字":"TOYAMA KEN","市区町村コード":"16211","市区町村名":"射水市","市区町村名カナ":"イミズシ","市区町村名ローマ字":"IMIZU SHI","大字町丁目コード":"162110002002","大字町丁目名":"あおば台二丁目","緯度":36.717888,"経度":137.051587},{"都道府県コード":"16","都道府県名":"富山県","都道府県名カナ":"トヤマケン","都道府県名ローマ字":"TOYAMA KEN","市区町村コード":"16211","市区町村名":"射水市","市区町村名カナ":"イミズシ","市区町村名ローマ字":"IMIZU SHI","大字町丁目コード":"162110003000","大字町丁目名":"赤井","緯度":36.727352,"経度":137.068045},{"都道府県コード":"16","都道府県名":"富山県","都道府県名カナ":"トヤマケン","都道府県名ローマ字":"TOYAMA KEN","市区町村コード":"16211","市区町村名":"射水市","市区町村名カナ":"イミズシ","市区町村名ローマ字":"IMIZU SHI","大字町丁目コード":"162110004001","大字町丁目名":"足洗新町一丁目","緯度":36.758652,"経度":137.167643},{"都道府県コード":"16","都道府県名":"富山県","都道府県名カナ":"トヤマケン","都道府県名ローマ字":"TOYAMA KEN","市区町村コード":"16211","市区町村名":"射水市","市区町村名カナ":"イミズシ","市区町村名ローマ字":"IMIZU SHI","大字町丁目コード":"162110005000","大字町丁目名":"荒町","緯度":36.696008,"経度":137.049148},{"都道府県コード":"16","都道府県名":"富山県","都道府県名カナ":"トヤマケン","都道府県名ローマ字":"TOYAMA KEN","市区町村コード":"16211","市区町村名":"射水市","市区町村名カナ":"イミズシ","市区町村名ローマ字":"IMIZU SHI","大字町丁目コード":"162110006001","大字町丁目名":"有磯一丁目","緯度":36.762533,"経度":137.14247},{"都道府県コード":"16","都道府県名":"富山県","都道府県名カナ":"トヤマケン","都道府県名ローマ字":"TOYAMA KEN","市区町村コード":"16211","市区町村名":"射水市","市区町村名カナ":"イミズシ","市区町村名ローマ字":"IMIZU SHI","大字町丁目コード":"162110006002","大字町丁目名":"有磯二丁目","緯度":36.759086,"経度":137.149903},{"都道府県コード":"16","都道府県名":"富山県","都道府県名カナ":"トヤマケン","都道府県名ローマ字":"TOYAMA KEN","市区町村コード":"16211","市区町村名":"射水市","市区町村名カナ":"イミズシ","市区町村名ローマ字":"IMIZU SHI","大字町丁目コード":"162110007000","大字町丁目名":"池多","緯度":36.690105,"経度":137.103865},{"都道府県コード":"16","都道府県名":"富山県","都道府県名カナ":"トヤマケン","都道府県名ローマ字":"TOYAMA KEN","市区町村コード":"16211","市区町村名":"射水市","市区町村名カナ":"イミズシ","市区町村名ローマ字":"IMIZU SHI","大字町丁目コード":"162110008000","大字町丁目名":"一条","緯度":36.713093,"経度":137.088193},{"都道府県コード":"16","都道府県名":"富山県","都道府県名カナ":"トヤマケン","都道府県名ローマ字":"TOYAMA KEN","市区町村コード":"16211","市区町村名":"射水市","市区町村名カナ":"イミズシ","市区町村名ローマ字":"IMIZU SHI","大字町丁目コード":"162110009000","大字町丁目名":"市井","緯度":36.706284,"経度":137.055267},{"都道府県コード":"16","都道府県名":"富山県","都道府県名カナ":"トヤマケン","都道府県名ローマ字":"TOYAMA KEN","市区町村コード":"16211","市区町村名":"射水市","市区町村名カナ":"イミズシ","市区町村名ローマ字":"IMIZU SHI","大字町丁目コード":"162110010000","大字町丁目名":"稲積","緯度":36.739127,"経度":137.107162},{"都道府県コード":"16","都道府県名":"富山県","都道府県名カナ":"トヤマケン","都道府県名ローマ字":"TOYAMA KEN","市区町村コード":"16211","市区町村名":"射水市","市区町村名カナ":"イミズシ","市区町村名ローマ字":"IMIZU SHI","大字町丁目コード":"162110011000","大字町丁目名":"今井","緯度":36.737637,"経度":137.087833},{"都道府県コード":"16","都道府県名":"富山県","都道府県名カナ":"トヤマケン","都道府県名ローマ字":"TOYAMA KEN","市区町村コード":"16211","市区町村名":"射水市","市区町村名カナ":"イミズシ","市区町村名ローマ字":"IMIZU SHI","大字町丁目コード":"162110012000","大字町丁目名":"今開発","緯度":36.730724,"経度":137.091792},{"都道府県コード":"16","都道府県名":"富山県","都道府県名カナ":"トヤマケン","都道府県名ローマ字":"TOYAMA KEN","市区町村コード":"16211","市区町村名":"射水市","市区町村名カナ":"イミズシ","市区町村名ローマ字":"IMIZU SHI","大字町丁目コード":"162110013001","大字町丁目名":"射水町一丁目","緯度":36.768749,"経度":137.12375},{"都道府県コード":"16","都道府県名":"富山県","都道府県名カナ":"トヤマケン","都道府県名ローマ字":"TOYAMA KEN","市区町村コード":"16211","市区町村名":"射水市","市区町村名カナ":"イミズシ","市区町村名ローマ字":"IMIZU SHI","大字町丁目コード":"162110013002","大字町丁目名":"射水町二丁目","緯度":36.768737,"経度":137.127348},{"都道府県コード":"16","都道府県名":"富山県","都道府県名カナ":"トヤマケン","都道府県名ローマ字":"TOYAMA KEN","市区町村コード":"16211","市区町村名":"射水市","市区町村名カナ":"イミズシ","市区町村名ローマ字":"IMIZU SHI","大字町丁目コード":"162110014000","大字町丁目名":"犬内","緯度":36.738214,"経度":137.04698},{"都道府県コード":"16","都道府県名":"富山県","都道府県名カナ":"トヤマケン","都道府県名ローマ字":"TOYAMA KEN","市区町村コード":"16211","市区町村名":"射水市","市区町村名カナ":"イミズシ","市区町村名ローマ字":"IMIZU SHI","大字町丁目コード":"162110015000","大字町丁目名":"梅木","緯度":36.68338,"経度":137.044923},{"都道府県コード":"16","都道府県名":"富山県","都道府県名カナ":"トヤマケン","都道府県名ローマ字":"TOYAMA KEN","市区町村コード":"16211","市区町村名":"射水市","市区町村名カナ":"イミズシ","市区町村名ローマ字":"IMIZU SHI","大字町丁目コード":"162110016000","大字町丁目名":"海老江","緯度":36.766848,"経度":137.145785},{"都道府県コード":"16","都道府県名":"富山県","都道府県名カナ":"トヤマケン","都道府県名ローマ字":"TOYAMA KEN","市区町村コード":"16211","市区町村名":"射水市","市区町村名カナ":"イミズシ","市区町村名ローマ字":"IMIZU SHI","大字町丁目コード":"162110017000","大字町丁目名":"海老江七軒","緯度":36.757254,"経度":137.154986},{"都道府県コード":"16","都道府県名":"富山県","都道府県名カナ":"トヤマケン","都道府県名ローマ字":"TOYAMA KEN","市区町村コード":"16211","市区町村名":"射水市","市区町村名カナ":"イミズシ","市区町村名ローマ字":"IMIZU SHI","大字町丁目コード":"162110018000","大字町丁目名":"海老江練合","緯度":36.759703,"経度":137.159528},{"都道府県コード":"16","都道府県名":"富山県","都道府県名カナ":"トヤマケン","都道府県名ローマ字":"TOYAMA KEN","市区町村コード":"16211","市区町村名":"射水市","市区町村名カナ":"イミズシ","市区町村名ローマ字":"IMIZU SHI","大字町丁目コード":"162110019000","大字町丁目名":"海老江浜開","緯度":36.768148,"経度":137.138803},{"都道府県コード":"16","都道府県名":"富山県","都道府県名カナ":"トヤマケン","都道府県名ローマ字":"TOYAMA KEN","市区町村コード":"16211","市区町村名":"射水市","市区町村名カナ":"イミズシ","市区町村名ローマ字":"IMIZU SHI","大字町丁目コード":"162110020000","大字町丁目名":"大江","緯度":36.732103,"経度":137.114396},{"都道府県コード":"16","都道府県名":"富山県","都道府県名カナ":"トヤマケン","都道府県名ローマ字":"TOYAMA KEN","市区町村コード":"16211","市区町村名":"射水市","市区町村名カナ":"イミズシ","市区町村名ローマ字":"IMIZU SHI","大字町丁目コード":"162110021000","大字町丁目名":"大島北野","緯度":36.746076,"経度":137.049066},{"都道府県コード":"16","都道府県名":"富山県","都道府県名カナ":"トヤマケン","都道府県名ローマ字":"TOYAMA KEN","市区町村コード":"16211","市区町村名":"射水市","市区町村名カナ":"イミズシ","市区町村名ローマ字":"IMIZU SHI","大字町丁目コード":"162110022000","大字町丁目名":"沖","緯度":36.737598,"経度":137.096394},{"都道府県コード":"16","都道府県名":"富山県","都道府県名カナ":"トヤマケン","都道府県名ローマ字":"TOYAMA KEN","市区町村コード":"16211","市区町村名":"射水市","市区町村名カナ":"イミズシ","市区町村名ローマ字":"IMIZU SHI","大字町丁目コード":"162110023000","大字町丁目名":"沖塚原","緯度":36.750901,"経度":137.072663},{"都道府県コード":"16","都道府県名":"富山県","都道府県名カナ":"トヤマケン","都道府県名ローマ字":"TOYAMA KEN","市区町村コード":"16211","市区町村名":"射水市","市区町村名カナ":"イミズシ","市区町村名ローマ字":"IMIZU SHI","大字町丁目コード":"162110024000","大字町丁目名":"海王町","緯度":36.780804,"経度":137.105892},{"都道府県コード":"16","都道府県名":"富山県","都道府県名カナ":"トヤマケン","都道府県名ローマ字":"TOYAMA KEN","市区町村コード":"16211","市区町村名":"射水市","市区町村名カナ":"イミズシ","市区町村名ローマ字":"IMIZU SHI","大字町丁目コード":"162110025000","大字町丁目名":"開口","緯度":36.711592,"経度":137.056914},{"都道府県コード":"16","都道府県名":"富山県","都道府県名カナ":"トヤマケン","都道府県名ローマ字":"TOYAMA KEN","市区町村コード":"16211","市区町村名":"射水市","市区町村名カナ":"イミズシ","市区町村名ローマ字":"IMIZU SHI","大字町丁目コード":"162110026000","大字町丁目名":"海竜新町","緯度":36.771338,"経度":137.135544},{"都道府県コード":"16","都道府県名":"富山県","都道府県名カナ":"トヤマケン","都道府県名ローマ字":"TOYAMA KEN","市区町村コード":"16211","市区町村名":"射水市","市区町村名カナ":"イミズシ","市区町村名ローマ字":"IMIZU SHI","大字町丁目コード":"162110027000","大字町丁目名":"海竜町","緯度":36.774858,"経度":137.128098},{"都道府県コード":"16","都道府県名":"富山県","都道府県名カナ":"トヤマケン","都道府県名ローマ字":"TOYAMA KEN","市区町村コード":"16211","市区町村名":"射水市","市区町村名カナ":"イミズシ","市区町村名ローマ字":"IMIZU SHI","大字町丁目コード":"162110028000","大字町丁目名":"鏡宮","緯度":36.752385,"経度":137.083277},{"都道府県コード":"16","都道府県名":"富山県","都道府県名カナ":"トヤマケン","都道府県名ローマ字":"TOYAMA KEN","市区町村コード":"16211","市区町村名":"射水市","市区町村名カナ":"イミズシ","市区町村名ローマ字":"IMIZU SHI","大字町丁目コード":"162110029001","大字町丁目名":"鏡宮弥生一丁目","緯度":36.758725,"経度":137.084508},{"都道府県コード":"16","都道府県名":"富山県","都道府県名カナ":"トヤマケン","都道府県名ローマ字":"TOYAMA KEN","市区町村コード":"16211","市区町村名":"射水市","市区町村名カナ":"イミズシ","市区町村名ローマ字":"IMIZU SHI","大字町丁目コード":"162110029002","大字町丁目名":"鏡宮弥生二丁目","緯度":36.757089,"経度":137.083906},{"都道府県コード":"16","都道府県名":"富山県","都道府県名カナ":"トヤマケン","都道府県名ローマ字":"TOYAMA KEN","市区町村コード":"16211","市区町村名":"射水市","市区町村名カナ":"イミズシ","市区町村名ローマ字":"IMIZU SHI","大字町丁目コード":"162110030000","大字町丁目名":"片口","緯度":36.760898,"経度":137.116497},{"都道府県コード":"16","都道府県名":"富山県","都道府県名カナ":"トヤマケン","都道府県名ローマ字":"TOYAMA KEN","市区町村コード":"16211","市区町村名":"射水市","市区町村名カナ":"イミズシ","市区町村名ローマ字":"IMIZU SHI","大字町丁目コード":"162110031000","大字町丁目名":"片口久々江","緯度":36.744219,"経度":137.117932},{"都道府県コード":"16","都道府県名":"富山県","都道府県名カナ":"トヤマケン","都道府県名ローマ字":"TOYAMA KEN","市区町村コード":"16211","市区町村名":"射水市","市区町村名カナ":"イミズシ","市区町村名ローマ字":"IMIZU SHI","大字町丁目コード":"162110032000","大字町丁目名":"片口高場","緯度":36.75116,"経度":137.115245},{"都道府県コード":"16","都道府県名":"富山県","都道府県名カナ":"トヤマケン","都道府県名ローマ字":"TOYAMA KEN","市区町村コード":"16211","市区町村名":"射水市","市区町村名カナ":"イミズシ","市区町村名ローマ字":"IMIZU SHI","大字町丁目コード":"162110033000","大字町丁目名":"加茂西部","緯度":36.739848,"経度":137.139853},{"都道府県コード":"16","都道府県名":"富山県","都道府県名カナ":"トヤマケン","都道府県名ローマ字":"TOYAMA KEN","市区町村コード":"16211","市区町村名":"射水市","市区町村名カナ":"イミズシ","市区町村名ローマ字":"IMIZU SHI","大字町丁目コード":"162110034000","大字町丁目名":"加茂中部","緯度":36.742916,"経度":137.148912},{"都道府県コード":"16","都道府県名":"富山県","都道府県名カナ":"トヤマケン","都道府県名ローマ字":"TOYAMA KEN","市区町村コード":"16211","市区町村名":"射水市","市区町村名カナ":"イミズシ","市区町村名ローマ字":"IMIZU SHI","大字町丁目コード":"162110035000","大字町丁目名":"加茂東部","緯度":36.749711,"経度":137.152589},{"都道府県コード":"16","都道府県名":"富山県","都道府県名カナ":"トヤマケン","都道府県名ローマ字":"TOYAMA KEN","市区町村コード":"16211","市区町村名":"射水市","市区町村名カナ":"イミズシ","市区町村名ローマ字":"IMIZU SHI","大字町丁目コード":"162110036000","大字町丁目名":"かもめ台","緯度":36.757511,"経度":137.176093},{"都道府県コード":"16","都道府県名":"富山県","都道府県名カナ":"トヤマケン","都道府県名ローマ字":"TOYAMA KEN","市区町村コード":"16211","市区町村名":"射水市","市区町村名カナ":"イミズシ","市区町村名ローマ字":"IMIZU SHI","大字町丁目コード":"162110037000","大字町丁目名":"北高木","緯度":36.742105,"経度":137.070444},{"都道府県コード":"16","都道府県名":"富山県","都道府県名カナ":"トヤマケン","都道府県名ローマ字":"TOYAMA KEN","市区町村コード":"16211","市区町村名":"射水市","市区町村名カナ":"イミズシ","市区町村名ローマ字":"IMIZU SHI","大字町丁目コード":"162110038000","大字町丁目名":"北野","緯度":36.733155,"経度":137.054078},{"都道府県コード":"16","都道府県名":"富山県","都道府県名カナ":"トヤマケン","都道府県名ローマ字":"TOYAMA KEN","市区町村コード":"16211","市区町村名":"射水市","市区町村名カナ":"イミズシ","市区町村名ローマ字":"IMIZU SHI","大字町丁目コード":"162110039000","大字町丁目名":"久々湊","緯度":36.7568,"経度":137.098081},{"都道府県コード":"16","都道府県名":"富山県","都道府県名カナ":"トヤマケン","都道府県名ローマ字":"TOYAMA KEN","市区町村コード":"16211","市区町村名":"射水市","市区町村名カナ":"イミズシ","市区町村名ローマ字":"IMIZU SHI","大字町丁目コード":"162110040001","大字町丁目名":"草岡町一丁目","緯度":36.76855,"経度":137.130078},{"都道府県コード":"16","都道府県名":"富山県","都道府県名カナ":"トヤマケン","都道府県名ローマ字":"TOYAMA KEN","市区町村コード":"16211","市区町村名":"射水市","市区町村名カナ":"イミズシ","市区町村名ローマ字":"IMIZU SHI","大字町丁目コード":"162110040002","大字町丁目名":"草岡町二丁目","緯度":36.76779,"経度":137.133205},{"都道府県コード":"16","都道府県名":"富山県","都道府県名カナ":"トヤマケン","都道府県名ローマ字":"TOYAMA KEN","市区町村コード":"16211","市区町村名":"射水市","市区町村名カナ":"イミズシ","市区町村名ローマ字":"IMIZU SHI","大字町丁目コード":"162110041000","大字町丁目名":"串田新","緯度":36.683297,"経度":137.039203},{"都道府県コード":"16","都道府県名":"富山県","都道府県名カナ":"トヤマケン","都道府県名ローマ字":"TOYAMA KEN","市区町村コード":"16211","市区町村名":"射水市","市区町村名カナ":"イミズシ","市区町村名ローマ字":"IMIZU SHI","大字町丁目コード":"162110042000","大字町丁目名":"倉垣小杉","緯度":36.732967,"経度":137.144782},{"都道府県コード":"16","都道府県名":"富山県","都道府県名カナ":"トヤマケン","都道府県名ローマ字":"TOYAMA KEN","市区町村コード":"16211","市区町村名":"射水市","市区町村名カナ":"イミズシ","市区町村名ローマ字":"IMIZU SHI","大字町丁目コード":"162110043000","大字町丁目名":"黒河","緯度":36.701649,"経度":137.109714},{"都道府県コード":"16","都道府県名":"富山県","都道府県名カナ":"トヤマケン","都道府県名ローマ字":"TOYAMA KEN","市区町村コード":"16211","市区町村名":"射水市","市区町村名カナ":"イミズシ","市区町村名ローマ字":"IMIZU SHI","大字町丁目コード":"162110044000","大字町丁目名":"黒河新","緯度":36.697694,"経度":137.110176},{"都道府県コード":"16","都道府県名":"富山県","都道府県名カナ":"トヤマケン","都道府県名ローマ字":"TOYAMA KEN","市区町村コード":"16211","市区町村名":"射水市","市区町村名カナ":"イミズシ","市区町村名ローマ字":"IMIZU SHI","大字町丁目コード":"162110045000","大字町丁目名":"下条","緯度":36.717079,"経度":137.043611},{"都道府県コード":"16","都道府県名":"富山県","都道府県名カナ":"トヤマケン","都道府県名ローマ字":"TOYAMA KEN","市区町村コード":"16211","市区町村名":"射水市","市区町村名カナ":"イミズシ","市区町村名ローマ字":"IMIZU SHI","大字町丁目コード":"162110046000","大字町丁目名":"下条新","緯度":36.713402,"経度":137.078474},{"都道府県コード":"16","都道府県名":"富山県","都道府県名カナ":"トヤマケン","都道府県名ローマ字":"TOYAMA KEN","市区町村コード":"16211","市区町村名":"射水市","市区町村名カナ":"イミズシ","市区町村名ローマ字":"IMIZU SHI","大字町丁目コード":"162110047000","大字町丁目名":"小泉","緯度":36.703552,"経度":137.031588},{"都道府県コード":"16","都道府県名":"富山県","都道府県名カナ":"トヤマケン","都道府県名ローマ字":"TOYAMA KEN","市区町村コード":"16211","市区町村名":"射水市","市区町村名カナ":"イミズシ","市区町村名ローマ字":"IMIZU SHI","大字町丁目コード":"162110048000","大字町丁目名":"越の潟町","緯度":36.775783,"経度":137.10656},{"都道府県コード":"16","都道府県名":"富山県","都道府県名カナ":"トヤマケン","都道府県名ローマ字":"TOYAMA KEN","市区町村コード":"16211","市区町村名":"射水市","市区町村名カナ":"イミズシ","市区町村名ローマ字":"IMIZU SHI","大字町丁目コード":"162110049000","大字町丁目名":"小島","緯度":36.736278,"経度":137.060647},{"都道府県コード":"16","都道府県名":"富山県","都道府県名カナ":"トヤマケン","都道府県名ローマ字":"TOYAMA KEN","市区町村コード":"16211","市区町村名":"射水市","市区町村名カナ":"イミズシ","市区町村名ローマ字":"IMIZU SHI","大字町丁目コード":"162110050000","大字町丁目名":"小杉北野","緯度":36.685561,"経度":137.11834},{"都道府県コード":"16","都道府県名":"富山県","都道府県名カナ":"トヤマケン","都道府県名ローマ字":"TOYAMA KEN","市区町村コード":"16211","市区町村名":"射水市","市区町村名カナ":"イミズシ","市区町村名ローマ字":"IMIZU SHI","大字町丁目コード":"162110051000","大字町丁目名":"小杉白石","緯度":36.729051,"経度":137.129285},{"都道府県コード":"16","都道府県名":"富山県","都道府県名カナ":"トヤマケン","都道府県名ローマ字":"TOYAMA KEN","市区町村コード":"16211","市区町村名":"射水市","市区町村名カナ":"イミズシ","市区町村名ローマ字":"IMIZU SHI","大字町丁目コード":"162110052000","大字町丁目名":"小林","緯度":36.734881,"経度":137.070534},{"都道府県コード":"16","都道府県名":"富山県","都道府県名カナ":"トヤマケン","都道府県名ローマ字":"TOYAMA KEN","市区町村コード":"16211","市区町村名":"射水市","市区町村名カナ":"イミズシ","市区町村名ローマ字":"IMIZU SHI","大字町丁目コード":"162110053000","大字町丁目名":"桜町","緯度":36.777418,"経度":137.083124},{"都道府県コード":"16","都道府県名":"富山県","都道府県名カナ":"トヤマケン","都道府県名ローマ字":"TOYAMA KEN","市区町村コード":"16211","市区町村名":"射水市","市区町村名カナ":"イミズシ","市区町村名ローマ字":"IMIZU SHI","大字町丁目コード":"162110054000","大字町丁目名":"三ケ","緯度":36.723987,"経度":137.089547},{"都道府県コード":"16","都道府県名":"富山県","都道府県名カナ":"トヤマケン","都道府県名ローマ字":"TOYAMA KEN","市区町村コード":"16211","市区町村名":"射水市","市区町村名カナ":"イミズシ","市区町村名ローマ字":"IMIZU SHI","大字町丁目コード":"162110055000","大字町丁目名":"椎土","緯度":36.688149,"経度":137.119251},{"都道府県コード":"16","都道府県名":"富山県","都道府県名カナ":"トヤマケン","都道府県名ローマ字":"TOYAMA KEN","市区町村コード":"16211","市区町村名":"射水市","市区町村名カナ":"イミズシ","市区町村名ローマ字":"IMIZU SHI","大字町丁目コード":"162110056000","大字町丁目名":"七美","緯度":36.752044,"経度":137.137344},{"都道府県コード":"16","都道府県名":"富山県","都道府県名カナ":"トヤマケン","都道府県名ローマ字":"TOYAMA KEN","市区町村コード":"16211","市区町村名":"射水市","市区町村名カナ":"イミズシ","市区町村名ローマ字":"IMIZU SHI","大字町丁目コード":"162110057001","大字町丁目名":"七美一丁目","緯度":36.755278,"経度":137.133504},{"都道府県コード":"16","都道府県名":"富山県","都道府県名カナ":"トヤマケン","都道府県名ローマ字":"TOYAMA KEN","市区町村コード":"16211","市区町村名":"射水市","市区町村名カナ":"イミズシ","市区町村名ローマ字":"IMIZU SHI","大字町丁目コード":"162110057002","大字町丁目名":"七美二丁目","緯度":36.754878,"経度":137.142122},{"都道府県コード":"16","都道府県名":"富山県","都道府県名カナ":"トヤマケン","都道府県名ローマ字":"TOYAMA KEN","市区町村コード":"16211","市区町村名":"射水市","市区町村名カナ":"イミズシ","市区町村名ローマ字":"IMIZU SHI","大字町丁目コード":"162110058000","大字町丁目名":"七美中野","緯度":36.759988,"経度":137.136919},{"都道府県コード":"16","都道府県名":"富山県","都道府県名カナ":"トヤマケン","都道府県名ローマ字":"TOYAMA KEN","市区町村コード":"16211","市区町村名":"射水市","市区町村名カナ":"イミズシ","市区町村名ローマ字":"IMIZU SHI","大字町丁目コード":"162110059000","大字町丁目名":"島","緯度":36.712389,"経度":137.039014},{"都道府県コード":"16","都道府県名":"富山県","都道府県名カナ":"トヤマケン","都道府県名ローマ字":"TOYAMA KEN","市区町村コード":"16211","市区町村名":"射水市","市区町村名カナ":"イミズシ","市区町村名ローマ字":"IMIZU SHI","大字町丁目コード":"162110060000","大字町丁目名":"下村三箇","緯度":36.750116,"経度":137.163333},{"都道府県コード":"16","都道府県名":"富山県","都道府県名カナ":"トヤマケン","都道府県名ローマ字":"TOYAMA KEN","市区町村コード":"16211","市区町村名":"射水市","市区町村名カナ":"イミズシ","市区町村名ローマ字":"IMIZU SHI","大字町丁目コード":"162110061000","大字町丁目名":"下若","緯度":36.718272,"経度":137.077446},{"都道府県コード":"16","都道府県名":"富山県","都道府県名カナ":"トヤマケン","都道府県名ローマ字":"TOYAMA KEN","市区町村コード":"16211","市区町村名":"射水市","市区町村名カナ":"イミズシ","市区町村名ローマ字":"IMIZU SHI","大字町丁目コード":"162110062000","大字町丁目名":"宿屋","緯度":36.694501,"経度":137.073109},{"都道府県コード":"16","都道府県名":"富山県","都道府県名カナ":"トヤマケン","都道府県名ローマ字":"TOYAMA KEN","市区町村コード":"16211","市区町村名":"射水市","市区町村名カナ":"イミズシ","市区町村名ローマ字":"IMIZU SHI","大字町丁目コード":"162110063000","大字町丁目名":"庄川本町","緯度":36.784885,"経度":137.071407},{"都道府県コード":"16","都道府県名":"富山県","都道府県名カナ":"トヤマケン","都道府県名ローマ字":"TOYAMA KEN","市区町村コード":"16211","市区町村名":"射水市","市区町村名カナ":"イミズシ","市区町村名ローマ字":"IMIZU SHI","大字町丁目コード":"162110064000","大字町丁目名":"生源寺","緯度":36.698128,"経度":137.060217},{"都道府県コード":"16","都道府県名":"富山県","都道府県名カナ":"トヤマケン","都道府県名ローマ字":"TOYAMA KEN","市区町村コード":"16211","市区町村名":"射水市","市区町村名カナ":"イミズシ","市区町村名ローマ字":"IMIZU SHI","大字町丁目コード":"162110065001","大字町丁目名":"庄西町一丁目","緯度":36.790015,"経度":137.071091},{"都道府県コード":"16","都道府県名":"富山県","都道府県名カナ":"トヤマケン","都道府県名ローマ字":"TOYAMA KEN","市区町村コード":"16211","市区町村名":"射水市","市区町村名カナ":"イミズシ","市区町村名ローマ字":"IMIZU SHI","大字町丁目コード":"162110065002","大字町丁目名":"庄西町二丁目","緯度":36.788425,"経度":137.06326},{"都道府県コード":"16","都道府県名":"富山県","都道府県名カナ":"トヤマケン","都道府県名ローマ字":"TOYAMA KEN","市区町村コード":"16211","市区町村名":"射水市","市区町村名カナ":"イミズシ","市区町村名ローマ字":"IMIZU SHI","大字町丁目コード":"162110066000","大字町丁目名":"浄土寺","緯度":36.676452,"経度":137.087177},{"都道府県コード":"16","都道府県名":"富山県","都道府県名カナ":"トヤマケン","都道府県名ローマ字":"TOYAMA KEN","市区町村コード":"16211","市区町村名":"射水市","市区町村名カナ":"イミズシ","市区町村名ローマ字":"IMIZU SHI","大字町丁目コード":"162110067000","大字町丁目名":"白石","緯度":36.733461,"経度":137.136209},{"都道府県コード":"16","都道府県名":"富山県","都道府県名カナ":"トヤマケン","都道府県名ローマ字":"TOYAMA KEN","市区町村コード":"16211","市区町村名":"射水市","市区町村名カナ":"イミズシ","市区町村名ローマ字":"IMIZU SHI","大字町丁目コード":"162110068000","大字町丁目名":"新開発","緯度":36.730782,"経度":137.076351},{"都道府県コード":"16","都道府県名":"富山県","都道府県名カナ":"トヤマケン","都道府県名ローマ字":"TOYAMA KEN","市区町村コード":"16211","市区町村名":"射水市","市区町村名カナ":"イミズシ","市区町村名ローマ字":"IMIZU SHI","大字町丁目コード":"162110069001","大字町丁目名":"新片町一丁目","緯度":36.758861,"経度":137.11361},{"都道府県コード":"16","都道府県名":"富山県","都道府県名カナ":"トヤマケン","都道府県名ローマ字":"TOYAMA KEN","市区町村コード":"16211","市区町村名":"射水市","市区町村名カナ":"イミズシ","市区町村名ローマ字":"IMIZU SHI","大字町丁目コード":"162110069002","大字町丁目名":"新片町二丁目","緯度":36.759419,"経度":137.115603},{"都道府県コード":"16","都道府県名":"富山県","都道府県名カナ":"トヤマケン","都道府県名ローマ字":"TOYAMA KEN","市区町村コード":"16211","市区町村名":"射水市","市区町村名カナ":"イミズシ","市区町村名ローマ字":"IMIZU SHI","大字町丁目コード":"162110069003","大字町丁目名":"新片町三丁目","緯度":36.758396,"経度":137.119529},{"都道府県コード":"16","都道府県名":"富山県","都道府県名カナ":"トヤマケン","都道府県名ローマ字":"TOYAMA KEN","市区町村コード":"16211","市区町村名":"射水市","市区町村名カナ":"イミズシ","市区町村名ローマ字":"IMIZU SHI","大字町丁目コード":"162110069004","大字町丁目名":"新片町四丁目","緯度":36.757215,"経度":137.119281},{"都道府県コード":"16","都道府県名":"富山県","都道府県名カナ":"トヤマケン","都道府県名ローマ字":"TOYAMA KEN","市区町村コード":"16211","市区町村名":"射水市","市区町村名カナ":"イミズシ","市区町村名ローマ字":"IMIZU SHI","大字町丁目コード":"162110069005","大字町丁目名":"新片町五丁目","緯度":36.757857,"経度":137.115722},{"都道府県コード":"16","都道府県名":"富山県","都道府県名カナ":"トヤマケン","都道府県名ローマ字":"TOYAMA KEN","市区町村コード":"16211","市区町村名":"射水市","市区町村名カナ":"イミズシ","市区町村名ローマ字":"IMIZU SHI","大字町丁目コード":"162110070000","大字町丁目名":"新堀","緯度":36.754243,"経度":137.124571},{"都道府県コード":"16","都道府県名":"富山県","都道府県名カナ":"トヤマケン","都道府県名ローマ字":"TOYAMA KEN","市区町村コード":"16211","市区町村名":"射水市","市区町村名カナ":"イミズシ","市区町村名ローマ字":"IMIZU SHI","大字町丁目コード":"162110071000","大字町丁目名":"摺出寺","緯度":36.744337,"経度":137.133495},{"都道府県コード":"16","都道府県名":"富山県","都道府県名カナ":"トヤマケン","都道府県名ローマ字":"TOYAMA KEN","市区町村コード":"16211","市区町村名":"射水市","市区町村名カナ":"イミズシ","市区町村名ローマ字":"IMIZU SHI","大字町丁目コード":"162110072000","大字町丁目名":"善光寺","緯度":36.77615,"経度":137.077368},{"都道府県コード":"16","都道府県名":"富山県","都道府県名カナ":"トヤマケン","都道府県名ローマ字":"TOYAMA KEN","市区町村コード":"16211","市区町村名":"射水市","市区町村名カナ":"イミズシ","市区町村名ローマ字":"IMIZU SHI","大字町丁目コード":"162110073000","大字町丁目名":"太閤町","緯度":36.709864,"経度":137.097715},{"都道府県コード":"16","都道府県名":"富山県","都道府県名カナ":"トヤマケン","都道府県名ローマ字":"TOYAMA KEN","市区町村コード":"16211","市区町村名":"射水市","市区町村名カナ":"イミズシ","市区町村名ローマ字":"IMIZU SHI","大字町丁目コード":"162110074001","大字町丁目名":"太閤山一丁目","緯度":36.709701,"経度":137.095284},{"都道府県コード":"16","都道府県名":"富山県","都道府県名カナ":"トヤマケン","都道府県名ローマ字":"TOYAMA KEN","市区町村コード":"16211","市区町村名":"射水市","市区町村名カナ":"イミズシ","市区町村名ローマ字":"IMIZU SHI","大字町丁目コード":"162110074002","大字町丁目名":"太閤山二丁目","緯度":36.706549,"経度":137.095006},{"都道府県コード":"16","都道府県名":"富山県","都道府県名カナ":"トヤマケン","都道府県名ローマ字":"TOYAMA KEN","市区町村コード":"16211","市区町村名":"射水市","市区町村名カナ":"イミズシ","市区町村名ローマ字":"IMIZU SHI","大字町丁目コード":"162110074003","大字町丁目名":"太閤山三丁目","緯度":36.70645,"経度":137.092875},{"都道府県コード":"16","都道府県名":"富山県","都道府県名カナ":"トヤマケン","都道府県名ローマ字":"TOYAMA KEN","市区町村コード":"16211","市区町村名":"射水市","市区町村名カナ":"イミズシ","市区町村名ローマ字":"IMIZU SHI","大字町丁目コード":"162110074004","大字町丁目名":"太閤山四丁目","緯度":36.705227,"経度":137.093783},{"都道府県コード":"16","都道府県名":"富山県","都道府県名カナ":"トヤマケン","都道府県名ローマ字":"TOYAMA KEN","市区町村コード":"16211","市区町村名":"射水市","市区町村名カナ":"イミズシ","市区町村名ローマ字":"IMIZU SHI","大字町丁目コード":"162110074005","大字町丁目名":"太閤山五丁目","緯度":36.704756,"経度":137.090393},{"都道府県コード":"16","都道府県名":"富山県","都道府県名カナ":"トヤマケン","都道府県名ローマ字":"TOYAMA KEN","市区町村コード":"16211","市区町村名":"射水市","市区町村名カナ":"イミズシ","市区町村名ローマ字":"IMIZU SHI","大字町丁目コード":"162110074006","大字町丁目名":"太閤山六丁目","緯度":36.704998,"経度":137.088068},{"都道府県コード":"16","都道府県名":"富山県","都道府県名カナ":"トヤマケン","都道府県名ローマ字":"TOYAMA KEN","市区町村コード":"16211","市区町村名":"射水市","市区町村名カナ":"イミズシ","市区町村名ローマ字":"IMIZU SHI","大字町丁目コード":"162110074007","大字町丁目名":"太閤山七丁目","緯度":36.706706,"経度":137.088399},{"都道府県コード":"16","都道府県名":"富山県","都道府県名カナ":"トヤマケン","都道府県名ローマ字":"TOYAMA KEN","市区町村コード":"16211","市区町村名":"射水市","市区町村名カナ":"イミズシ","市区町村名ローマ字":"IMIZU SHI","大字町丁目コード":"162110074008","大字町丁目名":"太閤山八丁目","緯度":36.70737,"経度":137.090773},{"都道府県コード":"16","都道府県名":"富山県","都道府県名カナ":"トヤマケン","都道府県名ローマ字":"TOYAMA KEN","市区町村コード":"16211","市区町村名":"射水市","市区町村名カナ":"イミズシ","市区町村名ローマ字":"IMIZU SHI","大字町丁目コード":"162110074009","大字町丁目名":"太閤山九丁目","緯度":36.708841,"経度":137.091732},{"都道府県コード":"16","都道府県名":"富山県","都道府県名カナ":"トヤマケン","都道府県名ローマ字":"TOYAMA KEN","市区町村コード":"16211","市区町村名":"射水市","市区町村名カナ":"イミズシ","市区町村名ローマ字":"IMIZU SHI","大字町丁目コード":"162110074010","大字町丁目名":"太閤山十丁目","緯度":36.710709,"経度":137.092279},{"都道府県コード":"16","都道府県名":"富山県","都道府県名カナ":"トヤマケン","都道府県名ローマ字":"TOYAMA KEN","市区町村コード":"16211","市区町村名":"射水市","市区町村名カナ":"イミズシ","市区町村名ローマ字":"IMIZU SHI","大字町丁目コード":"162110074011","大字町丁目名":"太閤山十一丁目","緯度":36.709467,"経度":137.09054},{"都道府県コード":"16","都道府県名":"富山県","都道府県名カナ":"トヤマケン","都道府県名ローマ字":"TOYAMA KEN","市区町村コード":"16211","市区町村名":"射水市","市区町村名カナ":"イミズシ","市区町村名ローマ字":"IMIZU SHI","大字町丁目コード":"162110075000","大字町丁目名":"大門","緯度":36.734461,"経度":137.049116},{"都道府県コード":"16","都道府県名":"富山県","都道府県名カナ":"トヤマケン","都道府県名ローマ字":"TOYAMA KEN","市区町村コード":"16211","市区町村名":"射水市","市区町村名カナ":"イミズシ","市区町村名ローマ字":"IMIZU SHI","大字町丁目コード":"162110076000","大字町丁目名":"大門島","緯度":36.720344,"経度":137.051872},{"都道府県コード":"16","都道府県名":"富山県","都道府県名カナ":"トヤマケン","都道府県名ローマ字":"TOYAMA KEN","市区町村コード":"16211","市区町村名":"射水市","市区町村名カナ":"イミズシ","市区町村名ローマ字":"IMIZU SHI","大字町丁目コード":"162110077000","大字町丁目名":"大門新","緯度":36.735024,"経度":137.045662},{"都道府県コード":"16","都道府県名":"富山県","都道府県名カナ":"トヤマケン","都道府県名ローマ字":"TOYAMA KEN","市区町村コード":"16211","市区町村名":"射水市","市区町村名カナ":"イミズシ","市区町村名ローマ字":"IMIZU SHI","大字町丁目コード":"162110078000","大字町丁目名":"大門本江","緯度":36.715086,"経度":137.055691},{"都道府県コード":"16","都道府県名":"富山県","都道府県名カナ":"トヤマケン","都道府県名ローマ字":"TOYAMA KEN","市区町村コード":"16211","市区町村名":"射水市","市区町村名カナ":"イミズシ","市区町村名ローマ字":"IMIZU SHI","大字町丁目コード":"162110079000","大字町丁目名":"高木","緯度":36.743219,"経度":137.083199},{"都道府県コード":"16","都道府県名":"富山県","都道府県名カナ":"トヤマケン","都道府県名ローマ字":"TOYAMA KEN","市区町村コード":"16211","市区町村名":"射水市","市区町村名カナ":"イミズシ","市区町村名ローマ字":"IMIZU SHI","大字町丁目コード":"162110080001","大字町丁目名":"高場新町一丁目","緯度":36.756009,"経度":137.116944},{"都道府県コード":"16","都道府県名":"富山県","都道府県名カナ":"トヤマケン","都道府県名ローマ字":"TOYAMA KEN","市区町村コード":"16211","市区町村名":"射水市","市区町村名カナ":"イミズシ","市区町村名ローマ字":"IMIZU SHI","大字町丁目コード":"162110080002","大字町丁目名":"高場新町二丁目","緯度":36.755807,"経度":137.114827},{"都道府県コード":"16","都道府県名":"富山県","都道府県名カナ":"トヤマケン","都道府県名ローマ字":"TOYAMA KEN","市区町村コード":"16211","市区町村名":"射水市","市区町村名カナ":"イミズシ","市区町村名ローマ字":"IMIZU SHI","大字町丁目コード":"162110080003","大字町丁目名":"高場新町三丁目","緯度":36.753869,"経度":137.115374},{"都道府県コード":"16","都道府県名":"富山県","都道府県名カナ":"トヤマケン","都道府県名ローマ字":"TOYAMA KEN","市区町村コード":"16211","市区町村名":"射水市","市区町村名カナ":"イミズシ","市区町村名ローマ字":"IMIZU SHI","大字町丁目コード":"162110080004","大字町丁目名":"高場新町四丁目","緯度":36.75237,"経度":137.115566},{"都道府県コード":"16","都道府県名":"富山県","都道府県名カナ":"トヤマケン","都道府県名ローマ字":"TOYAMA KEN","市区町村コード":"16211","市区町村名":"射水市","市区町村名カナ":"イミズシ","市区町村名ローマ字":"IMIZU SHI","大字町丁目コード":"162110081000","大字町丁目名":"竹鼻","緯度":36.711843,"経度":137.062937},{"都道府県コード":"16","都道府県名":"富山県","都道府県名カナ":"トヤマケン","都道府県名ローマ字":"TOYAMA KEN","市区町村コード":"16211","市区町村名":"射水市","市区町村名カナ":"イミズシ","市区町村名ローマ字":"IMIZU SHI","大字町丁目コード":"162110082000","大字町丁目名":"立町","緯度":36.779855,"経度":137.088348},{"都道府県コード":"16","都道府県名":"富山県","都道府県名カナ":"トヤマケン","都道府県名ローマ字":"TOYAMA KEN","市区町村コード":"16211","市区町村名":"射水市","市区町村名カナ":"イミズシ","市区町村名ローマ字":"IMIZU SHI","大字町丁目コード":"162110083000","大字町丁目名":"棚田","緯度":36.718978,"経度":137.061446},{"都道府県コード":"16","都道府県名":"富山県","都道府県名カナ":"トヤマケン","都道府県名ローマ字":"TOYAMA KEN","市区町村コード":"16211","市区町村名":"射水市","市区町村名カナ":"イミズシ","市区町村名ローマ字":"IMIZU SHI","大字町丁目コード":"162110084000","大字町丁目名":"中央町","緯度":36.779452,"経度":137.084705},{"都道府県コード":"16","都道府県名":"富山県","都道府県名カナ":"トヤマケン","都道府県名ローマ字":"TOYAMA KEN","市区町村コード":"16211","市区町村名":"射水市","市区町村名カナ":"イミズシ","市区町村名ローマ字":"IMIZU SHI","大字町丁目コード":"162110085000","大字町丁目名":"塚越","緯度":36.698807,"経度":137.121174},{"都道府県コード":"16","都道府県名":"富山県","都道府県名カナ":"トヤマケン","都道府県名ローマ字":"TOYAMA KEN","市区町村コード":"16211","市区町村名":"射水市","市区町村名カナ":"イミズシ","市区町村名ローマ字":"IMIZU SHI","大字町丁目コード":"162110086000","大字町丁目名":"津幡江","緯度":36.749015,"経度":137.106769},{"都道府県コード":"16","都道府県名":"富山県","都道府県名カナ":"トヤマケン","都道府県名ローマ字":"TOYAMA KEN","市区町村コード":"16211","市区町村名":"射水市","市区町村名カナ":"イミズシ","市区町村名ローマ字":"IMIZU SHI","大字町丁目コード":"162110087000","大字町丁目名":"円池","緯度":36.699697,"経度":137.053175},{"都道府県コード":"16","都道府県名":"富山県","都道府県名カナ":"トヤマケン","都道府県名ローマ字":"TOYAMA KEN","市区町村コード":"16211","市区町村名":"射水市","市区町村名カナ":"イミズシ","市区町村名ローマ字":"IMIZU SHI","大字町丁目コード":"162110088000","大字町丁目名":"手崎","緯度":36.720942,"経度":137.116878},{"都道府県コード":"16","都道府県名":"富山県","都道府県名カナ":"トヤマケン","都道府県名ローマ字":"TOYAMA KEN","市区町村コード":"16211","市区町村名":"射水市","市区町村名カナ":"イミズシ","市区町村名ローマ字":"IMIZU SHI","大字町丁目コード":"162110089000","大字町丁目名":"寺塚原","緯度":36.752595,"経度":137.056792},{"都道府県コード":"16","都道府県名":"富山県","都道府県名カナ":"トヤマケン","都道府県名ローマ字":"TOYAMA KEN","市区町村コード":"16211","市区町村名":"射水市","市区町村名カナ":"イミズシ","市区町村名ローマ字":"IMIZU SHI","大字町丁目コード":"162110090000","大字町丁目名":"東明七軒","緯度":36.761457,"経度":137.153343},{"都道府県コード":"16","都道府県名":"富山県","都道府県名カナ":"トヤマケン","都道府県名ローマ字":"TOYAMA KEN","市区町村コード":"16211","市区町村名":"射水市","市区町村名カナ":"イミズシ","市区町村名ローマ字":"IMIZU SHI","大字町丁目コード":"162110091000","大字町丁目名":"東明中町","緯度":36.763662,"経度":137.147486},{"都道府県コード":"16","都道府県名":"富山県","都道府県名カナ":"トヤマケン","都道府県名ローマ字":"TOYAMA KEN","市区町村コード":"16211","市区町村名":"射水市","市区町村名カナ":"イミズシ","市区町村名ローマ字":"IMIZU SHI","大字町丁目コード":"162110092000","大字町丁目名":"東明西町","緯度":36.76531,"経度":137.143442},{"都道府県コード":"16","都道府県名":"富山県","都道府県名カナ":"トヤマケン","都道府県名ローマ字":"TOYAMA KEN","市区町村コード":"16211","市区町村名":"射水市","市区町村名カナ":"イミズシ","市区町村名ローマ字":"IMIZU SHI","大字町丁目コード":"162110093000","大字町丁目名":"東明東町","緯度":36.762444,"経度":137.150143},{"都道府県コード":"16","都道府県名":"富山県","都道府県名カナ":"トヤマケン","都道府県名ローマ字":"TOYAMA KEN","市区町村コード":"16211","市区町村名":"射水市","市区町村名カナ":"イミズシ","市区町村名ローマ字":"IMIZU SHI","大字町丁目コード":"162110094000","大字町丁目名":"土代","緯度":36.692531,"経度":137.116143},{"都道府県コード":"16","都道府県名":"富山県","都道府県名カナ":"トヤマケン","都道府県名ローマ字":"TOYAMA KEN","市区町村コード":"16211","市区町村名":"射水市","市区町村名カナ":"イミズシ","市区町村名ローマ字":"IMIZU SHI","大字町丁目コード":"162110095000","大字町丁目名":"鳥取","緯度":36.737001,"経度":137.077258},{"都道府県コード":"16","都道府県名":"富山県","都道府県名カナ":"トヤマケン","都道府県名ローマ字":"TOYAMA KEN","市区町村コード":"16211","市区町村名":"射水市","市区町村名カナ":"イミズシ","市区町村名ローマ字":"IMIZU SHI","大字町丁目コード":"162110096000","大字町丁目名":"殿村","緯度":36.74522,"経度":137.091512},{"都道府県コード":"16","都道府県名":"富山県","都道府県名カナ":"トヤマケン","都道府県名ローマ字":"TOYAMA KEN","市区町村コード":"16211","市区町村名":"射水市","市区町村名カナ":"イミズシ","市区町村名ローマ字":"IMIZU SHI","大字町丁目コード":"162110097000","大字町丁目名":"中老田","緯度":36.697183,"経度":137.119075},{"都道府県コード":"16","都道府県名":"富山県","都道府県名カナ":"トヤマケン","都道府県名ローマ字":"TOYAMA KEN","市区町村コード":"16211","市区町村名":"射水市","市区町村名カナ":"イミズシ","市区町村名ローマ字":"IMIZU SHI","大字町丁目コード":"162110098000","大字町丁目名":"中老田新","緯度":36.700929,"経度":137.116387},{"都道府県コード":"16","都道府県名":"富山県","都道府県名カナ":"トヤマケン","都道府県名ローマ字":"TOYAMA KEN","市区町村コード":"16211","市区町村名":"射水市","市区町村名カナ":"イミズシ","市区町村名ローマ字":"IMIZU SHI","大字町丁目コード":"162110099000","大字町丁目名":"中新湊","緯度":36.776873,"経度":137.08832},{"都道府県コード":"16","都道府県名":"富山県","都道府県名カナ":"トヤマケン","都道府県名ローマ字":"TOYAMA KEN","市区町村コード":"16211","市区町村名":"射水市","市区町村名カナ":"イミズシ","市区町村名ローマ字":"IMIZU SHI","大字町丁目コード":"162110100001","大字町丁目名":"中太閤山一丁目","緯度":36.703789,"経度":137.095801},{"都道府県コード":"16","都道府県名":"富山県","都道府県名カナ":"トヤマケン","都道府県名ローマ字":"TOYAMA KEN","市区町村コード":"16211","市区町村名":"射水市","市区町村名カナ":"イミズシ","市区町村名ローマ字":"IMIZU SHI","大字町丁目コード":"162110100002","大字町丁目名":"中太閤山二丁目","緯度":36.703567,"経度":137.093087},{"都道府県コード":"16","都道府県名":"富山県","都道府県名カナ":"トヤマケン","都道府県名ローマ字":"TOYAMA KEN","市区町村コード":"16211","市区町村名":"射水市","市区町村名カナ":"イミズシ","市区町村名ローマ字":"IMIZU SHI","大字町丁目コード":"162110100003","大字町丁目名":"中太閤山三丁目","緯度":36.702001,"経度":137.093318},{"都道府県コード":"16","都道府県名":"富山県","都道府県名カナ":"トヤマケン","都道府県名ローマ字":"TOYAMA KEN","市区町村コード":"16211","市区町村名":"射水市","市区町村名カナ":"イミズシ","市区町村名ローマ字":"IMIZU SHI","大字町丁目コード":"162110100004","大字町丁目名":"中太閤山四丁目","緯度":36.702886,"経度":137.090498},{"都道府県コード":"16","都道府県名":"富山県","都道府県名カナ":"トヤマケン","都道府県名ローマ字":"TOYAMA KEN","市区町村コード":"16211","市区町村名":"射水市","市区町村名カナ":"イミズシ","市区町村名ローマ字":"IMIZU SHI","大字町丁目コード":"162110100005","大字町丁目名":"中太閤山五丁目","緯度":36.703574,"経度":137.088209},{"都道府県コード":"16","都道府県名":"富山県","都道府県名カナ":"トヤマケン","都道府県名ローマ字":"TOYAMA KEN","市区町村コード":"16211","市区町村名":"射水市","市区町村名カナ":"イミズシ","市区町村名ローマ字":"IMIZU SHI","大字町丁目コード":"162110100006","大字町丁目名":"中太閤山六丁目","緯度":36.703068,"経度":137.085928},{"都道府県コード":"16","都道府県名":"富山県","都道府県名カナ":"トヤマケン","都道府県名ローマ字":"TOYAMA KEN","市区町村コード":"16211","市区町村名":"射水市","市区町村名カナ":"イミズシ","市区町村名ローマ字":"IMIZU SHI","大字町丁目コード":"162110100007","大字町丁目名":"中太閤山七丁目","緯度":36.702095,"経度":137.088853},{"都道府県コード":"16","都道府県名":"富山県","都道府県名カナ":"トヤマケン","都道府県名ローマ字":"TOYAMA KEN","市区町村コード":"16211","市区町村名":"射水市","市区町村名カナ":"イミズシ","市区町村名ローマ字":"IMIZU SHI","大字町丁目コード":"162110100008","大字町丁目名":"中太閤山八丁目","緯度":36.700675,"経度":137.091007},{"都道府県コード":"16","都道府県名":"富山県","都道府県名カナ":"トヤマケン","都道府県名ローマ字":"TOYAMA KEN","市区町村コード":"16211","市区町村名":"射水市","市区町村名カナ":"イミズシ","市区町村名ローマ字":"IMIZU SHI","大字町丁目コード":"162110100009","大字町丁目名":"中太閤山九丁目","緯度":36.699995,"経度":137.092505},{"都道府県コード":"16","都道府県名":"富山県","都道府県名カナ":"トヤマケン","都道府県名ローマ字":"TOYAMA KEN","市区町村コード":"16211","市区町村名":"射水市","市区町村名カナ":"イミズシ","市区町村名ローマ字":"IMIZU SHI","大字町丁目コード":"162110100010","大字町丁目名":"中太閤山十丁目","緯度":36.701111,"経度":137.092912},{"都道府県コード":"16","都道府県名":"富山県","都道府県名カナ":"トヤマケン","都道府県名ローマ字":"TOYAMA KEN","市区町村コード":"16211","市区町村名":"射水市","市区町村名カナ":"イミズシ","市区町村名ローマ字":"IMIZU SHI","大字町丁目コード":"162110100011","大字町丁目名":"中太閤山十一丁目","緯度":36.701288,"経度":137.094978},{"都道府県コード":"16","都道府県名":"富山県","都道府県名カナ":"トヤマケン","都道府県名ローマ字":"TOYAMA KEN","市区町村コード":"16211","市区町村名":"射水市","市区町村名カナ":"イミズシ","市区町村名ローマ字":"IMIZU SHI","大字町丁目コード":"162110100012","大字町丁目名":"中太閤山十二丁目","緯度":36.702236,"経度":137.09641},{"都道府県コード":"16","都道府県名":"富山県","都道府県名カナ":"トヤマケン","都道府県名ローマ字":"TOYAMA KEN","市区町村コード":"16211","市区町村名":"射水市","市区町村名カナ":"イミズシ","市区町村名ローマ字":"IMIZU SHI","大字町丁目コード":"162110100013","大字町丁目名":"中太閤山十三丁目","緯度":36.700855,"経度":137.096125},{"都道府県コード":"16","都道府県名":"富山県","都道府県名カナ":"トヤマケン","都道府県名ローマ字":"TOYAMA KEN","市区町村コード":"16211","市区町村名":"射水市","市区町村名カナ":"イミズシ","市区町村名ローマ字":"IMIZU SHI","大字町丁目コード":"162110100014","大字町丁目名":"中太閤山十四丁目","緯度":36.701038,"経度":137.097438},{"都道府県コード":"16","都道府県名":"富山県","都道府県名カナ":"トヤマケン","都道府県名ローマ字":"TOYAMA KEN","市区町村コード":"16211","市区町村名":"射水市","市区町村名カナ":"イミズシ","市区町村名ローマ字":"IMIZU SHI","大字町丁目コード":"162110100015","大字町丁目名":"中太閤山十五丁目","緯度":36.703766,"経度":137.097999},{"都道府県コード":"16","都道府県名":"富山県","都道府県名カナ":"トヤマケン","都道府県名ローマ字":"TOYAMA KEN","市区町村コード":"16211","市区町村名":"射水市","市区町村名カナ":"イミズシ","市区町村名ローマ字":"IMIZU SHI","大字町丁目コード":"162110100016","大字町丁目名":"中太閤山十六丁目","緯度":36.701828,"経度":137.098942},{"都道府県コード":"16","都道府県名":"富山県","都道府県名カナ":"トヤマケン","都道府県名ローマ字":"TOYAMA KEN","市区町村コード":"16211","市区町村名":"射水市","市区町村名カナ":"イミズシ","市区町村名ローマ字":"IMIZU SHI","大字町丁目コード":"162110100017","大字町丁目名":"中太閤山十七丁目","緯度":36.699447,"経度":137.099908},{"都道府県コード":"16","都道府県名":"富山県","都道府県名カナ":"トヤマケン","都道府県名ローマ字":"TOYAMA KEN","市区町村コード":"16211","市区町村名":"射水市","市区町村名カナ":"イミズシ","市区町村名ローマ字":"IMIZU SHI","大字町丁目コード":"162110100018","大字町丁目名":"中太閤山十八丁目","緯度":36.699301,"経度":137.089717},{"都道府県コード":"16","都道府県名":"富山県","都道府県名カナ":"トヤマケン","都道府県名ローマ字":"TOYAMA KEN","市区町村コード":"16211","市区町村名":"射水市","市区町村名カナ":"イミズシ","市区町村名ローマ字":"IMIZU SHI","大字町丁目コード":"162110100019","大字町丁目名":"中太閤山十九丁目","緯度":36.700567,"経度":137.086356},{"都道府県コード":"16","都道府県名":"富山県","都道府県名カナ":"トヤマケン","都道府県名ローマ字":"TOYAMA KEN","市区町村コード":"16211","市区町村名":"射水市","市区町村名カナ":"イミズシ","市区町村名ローマ字":"IMIZU SHI","大字町丁目コード":"162110101000","大字町丁目名":"中野","緯度":36.742225,"経度":137.059505},{"都道府県コード":"16","都道府県名":"富山県","都道府県名カナ":"トヤマケン","都道府県名ローマ字":"TOYAMA KEN","市区町村コード":"16211","市区町村名":"射水市","市区町村名カナ":"イミズシ","市区町村名ローマ字":"IMIZU SHI","大字町丁目コード":"162110102000","大字町丁目名":"中村","緯度":36.721949,"経度":137.054395},{"都道府県コード":"16","都道府県名":"富山県","都道府県名カナ":"トヤマケン","都道府県名ローマ字":"TOYAMA KEN","市区町村コード":"16211","市区町村名":"射水市","市区町村名カナ":"イミズシ","市区町村名ローマ字":"IMIZU SHI","大字町丁目コード":"162110103000","大字町丁目名":"奈呉の江","緯度":36.762551,"経度":137.10034},{"都道府県コード":"16","都道府県名":"富山県","都道府県名カナ":"トヤマケン","都道府県名ローマ字":"TOYAMA KEN","市区町村コード":"16211","市区町村名":"射水市","市区町村名カナ":"イミズシ","市区町村名ローマ字":"IMIZU SHI","大字町丁目コード":"162110104000","大字町丁目名":"西新湊","緯度":36.780411,"経度":137.076429},{"都道府県コード":"16","都道府県名":"富山県","都道府県名カナ":"トヤマケン","都道府県名ローマ字":"TOYAMA KEN","市区町村コード":"16211","市区町村名":"射水市","市区町村名カナ":"イミズシ","市区町村名ローマ字":"IMIZU SHI","大字町丁目コード":"162110105000","大字町丁目名":"西高木","緯度":36.742316,"経度":137.123593},{"都道府県コード":"16","都道府県名":"富山県","都道府県名カナ":"トヤマケン","都道府県名ローマ字":"TOYAMA KEN","市区町村コード":"16211","市区町村名":"射水市","市区町村名カナ":"イミズシ","市区町村名ローマ字":"IMIZU SHI","大字町丁目コード":"162110106000","大字町丁目名":"西広上","緯度":36.702018,"経度":137.015628},{"都道府県コード":"16","都道府県名":"富山県","都道府県名カナ":"トヤマケン","都道府県名ローマ字":"TOYAMA KEN","市区町村コード":"16211","市区町村名":"射水市","市区町村名カナ":"イミズシ","市区町村名ローマ字":"IMIZU SHI","大字町丁目コード":"162110107000","大字町丁目名":"二の丸町","緯度":36.77446,"経度":137.091971},{"都道府県コード":"16","都道府県名":"富山県","都道府県名カナ":"トヤマケン","都道府県名ローマ字":"TOYAMA KEN","市区町村コード":"16211","市区町村名":"射水市","市区町村名カナ":"イミズシ","市区町村名ローマ字":"IMIZU SHI","大字町丁目コード":"162110108000","大字町丁目名":"布目","緯度":36.746302,"経度":137.08019},{"都道府県コード":"16","都道府県名":"富山県","都道府県名カナ":"トヤマケン","都道府県名ローマ字":"TOYAMA KEN","市区町村コード":"16211","市区町村名":"射水市","市区町村名カナ":"イミズシ","市区町村名ローマ字":"IMIZU SHI","大字町丁目コード":"162110109000","大字町丁目名":"布目沢","緯度":36.702897,"経度":137.045855},{"都道府県コード":"16","都道府県名":"富山県","都道府県名カナ":"トヤマケン","都道府県名ローマ字":"TOYAMA KEN","市区町村コード":"16211","市区町村名":"射水市","市区町村名カナ":"イミズシ","市区町村名ローマ字":"IMIZU SHI","大字町丁目コード":"162110110000","大字町丁目名":"野手","緯度":36.665986,"経度":137.066943},{"都道府県コード":"16","都道府県名":"富山県","都道府県名カナ":"トヤマケン","都道府県名ローマ字":"TOYAMA KEN","市区町村コード":"16211","市区町村名":"射水市","市区町村名カナ":"イミズシ","市区町村名ローマ字":"IMIZU SHI","大字町丁目コード":"162110111000","大字町丁目名":"野村","緯度":36.750598,"経度":137.098501},{"都道府県コード":"16","都道府県名":"富山県","都道府県名カナ":"トヤマケン","都道府県名ローマ字":"TOYAMA KEN","市区町村コード":"16211","市区町村名":"射水市","市区町村名カナ":"イミズシ","市区町村名ローマ字":"IMIZU SHI","大字町丁目コード":"162110112000","大字町丁目名":"橋下条","緯度":36.707763,"経度":137.081548},{"都道府県コード":"16","都道府県名":"富山県","都道府県名カナ":"トヤマケン","都道府県名ローマ字":"TOYAMA KEN","市区町村コード":"16211","市区町村名":"射水市","市区町村名カナ":"イミズシ","市区町村名ローマ字":"IMIZU SHI","大字町丁目コード":"162110113001","大字町丁目名":"八幡町一丁目","緯度":36.78169,"経度":137.091582},{"都道府県コード":"16","都道府県名":"富山県","都道府県名カナ":"トヤマケン","都道府県名ローマ字":"TOYAMA KEN","市区町村コード":"16211","市区町村名":"射水市","市区町村名カナ":"イミズシ","市区町村名ローマ字":"IMIZU SHI","大字町丁目コード":"162110113002","大字町丁目名":"八幡町二丁目","緯度":36.779357,"経度":137.096656},{"都道府県コード":"16","都道府県名":"富山県","都道府県名カナ":"トヤマケン","都道府県名ローマ字":"TOYAMA KEN","市区町村コード":"16211","市区町村名":"射水市","市区町村名カナ":"イミズシ","市区町村名ローマ字":"IMIZU SHI","大字町丁目コード":"162110113003","大字町丁目名":"八幡町三丁目","緯度":36.776233,"経度":137.097511},{"都道府県コード":"16","都道府県名":"富山県","都道府県名カナ":"トヤマケン","都道府県名ローマ字":"TOYAMA KEN","市区町村コード":"16211","市区町村名":"射水市","市区町村名カナ":"イミズシ","市区町村名ローマ字":"IMIZU SHI","大字町丁目コード":"162110114000","大字町丁目名":"八講","緯度":36.742786,"経度":137.128123},{"都道府県コード":"16","都道府県名":"富山県","都道府県名カナ":"トヤマケン","都道府県名ローマ字":"TOYAMA KEN","市区町村コード":"16211","市区町村名":"射水市","市区町村名カナ":"イミズシ","市区町村名ローマ字":"IMIZU SHI","大字町丁目コード":"162110115000","大字町丁目名":"浜開新町","緯度":36.766833,"経度":137.138088},{"都道府県コード":"16","都道府県名":"富山県","都道府県名カナ":"トヤマケン","都道府県名ローマ字":"TOYAMA KEN","市区町村コード":"16211","市区町村名":"射水市","市区町村名カナ":"イミズシ","市区町村名ローマ字":"IMIZU SHI","大字町丁目コード":"162110116000","大字町丁目名":"坂東","緯度":36.755964,"経度":137.057095},{"都道府県コード":"16","都道府県名":"富山県","都道府県名カナ":"トヤマケン","都道府県名ローマ字":"TOYAMA KEN","市区町村コード":"16211","市区町村名":"射水市","市区町村名カナ":"イミズシ","市区町村名ローマ字":"IMIZU SHI","大字町丁目コード":"162110117001","大字町丁目名":"東太閤山一丁目","緯度":36.70014,"経度":137.117846},{"都道府県コード":"16","都道府県名":"富山県","都道府県名カナ":"トヤマケン","都道府県名ローマ字":"TOYAMA KEN","市区町村コード":"16211","市区町村名":"射水市","市区町村名カナ":"イミズシ","市区町村名ローマ字":"IMIZU SHI","大字町丁目コード":"162110117002","大字町丁目名":"東太閤山二丁目","緯度":36.699229,"経度":137.117613},{"都道府県コード":"16","都道府県名":"富山県","都道府県名カナ":"トヤマケン","都道府県名ローマ字":"TOYAMA KEN","市区町村コード":"16211","市区町村名":"射水市","市区町村名カナ":"イミズシ","市区町村名ローマ字":"IMIZU SHI","大字町丁目コード":"162110117003","大字町丁目名":"東太閤山三丁目","緯度":36.698119,"経度":137.117458},{"都道府県コード":"16","都道府県名":"富山県","都道府県名カナ":"トヤマケン","都道府県名ローマ字":"TOYAMA KEN","市区町村コード":"16211","市区町村名":"射水市","市区町村名カナ":"イミズシ","市区町村名ローマ字":"IMIZU SHI","大字町丁目コード":"162110117004","大字町丁目名":"東太閤山四丁目","緯度":36.698082,"経度":137.115376},{"都道府県コード":"16","都道府県名":"富山県","都道府県名カナ":"トヤマケン","都道府県名ローマ字":"TOYAMA KEN","市区町村コード":"16211","市区町村名":"射水市","市区町村名カナ":"イミズシ","市区町村名ローマ字":"IMIZU SHI","大字町丁目コード":"162110118000","大字町丁目名":"日宮","緯度":36.703985,"経度":137.085362},{"都道府県コード":"16","都道府県名":"富山県","都道府県名カナ":"トヤマケン","都道府県名ローマ字":"TOYAMA KEN","市区町村コード":"16211","市区町村名":"射水市","市区町村名カナ":"イミズシ","市区町村名ローマ字":"IMIZU SHI","大字町丁目コード":"162110119000","大字町丁目名":"戸破","緯度":36.721682,"経度":137.110661},{"都道府県コード":"16","都道府県名":"富山県","都道府県名カナ":"トヤマケン","都道府県名ローマ字":"TOYAMA KEN","市区町村コード":"16211","市区町村名":"射水市","市区町村名カナ":"イミズシ","市区町村名ローマ字":"IMIZU SHI","大字町丁目コード":"162110120000","大字町丁目名":"平野","緯度":36.689227,"経度":137.09638},{"都道府県コード":"16","都道府県名":"富山県","都道府県名カナ":"トヤマケン","都道府県名ローマ字":"TOYAMA KEN","市区町村コード":"16211","市区町村名":"射水市","市区町村名カナ":"イミズシ","市区町村名ローマ字":"IMIZU SHI","大字町丁目コード":"162110121000","大字町丁目名":"広上","緯度":36.703815,"経度":137.023792},{"都道府県コード":"16","都道府県名":"富山県","都道府県名カナ":"トヤマケン","都道府県名ローマ字":"TOYAMA KEN","市区町村コード":"16211","市区町村名":"射水市","市区町村名カナ":"イミズシ","市区町村名ローマ字":"IMIZU SHI","大字町丁目コード":"162110122000","大字町丁目名":"枇杷首","緯度":36.735323,"経度":137.041358},{"都道府県コード":"16","都道府県名":"富山県","都道府県名カナ":"トヤマケン","都道府県名ローマ字":"TOYAMA KEN","市区町村コード":"16211","市区町村名":"射水市","市区町村名カナ":"イミズシ","市区町村名ローマ字":"IMIZU SHI","大字町丁目コード":"162110123000","大字町丁目名":"藤巻","緯度":36.710142,"経度":137.052856},{"都道府県コード":"16","都道府県名":"富山県","都道府県名カナ":"トヤマケン","都道府県名ローマ字":"TOYAMA KEN","市区町村コード":"16211","市区町村名":"射水市","市区町村名カナ":"イミズシ","市区町村名ローマ字":"IMIZU SHI","大字町丁目コード":"162110124000","大字町丁目名":"二口","緯度":36.725469,"経度":137.056105},{"都道府県コード":"16","都道府県名":"富山県","都道府県名カナ":"トヤマケン","都道府県名ローマ字":"TOYAMA KEN","市区町村コード":"16211","市区町村名":"射水市","市区町村名カナ":"イミズシ","市区町村名ローマ字":"IMIZU SHI","大字町丁目コード":"162110125000","大字町丁目名":"放生津町","緯度":36.782602,"経度":137.085896},{"都道府県コード":"16","都道府県名":"富山県","都道府県名カナ":"トヤマケン","都道府県名ローマ字":"TOYAMA KEN","市区町村コード":"16211","市区町村名":"射水市","市区町村名カナ":"イミズシ","市区町村名ローマ字":"IMIZU SHI","大字町丁目コード":"162110126000","大字町丁目名":"朴木","緯度":36.757772,"経度":137.078532},{"都道府県コード":"16","都道府県名":"富山県","都道府県名カナ":"トヤマケン","都道府県名ローマ字":"TOYAMA KEN","市区町村コード":"16211","市区町村名":"射水市","市区町村名カナ":"イミズシ","市区町村名ローマ字":"IMIZU SHI","大字町丁目コード":"162110127000","大字町丁目名":"堀江千石","緯度":36.766351,"経度":137.125299},{"都道府県コード":"16","都道府県名":"富山県","都道府県名カナ":"トヤマケン","都道府県名ローマ字":"TOYAMA KEN","市区町村コード":"16211","市区町村名":"射水市","市区町村名カナ":"イミズシ","市区町村名ローマ字":"IMIZU SHI","大字町丁目コード":"162110128000","大字町丁目名":"堀岡","緯度":36.772064,"経度":137.124083},{"都道府県コード":"16","都道府県名":"富山県","都道府県名カナ":"トヤマケン","都道府県名ローマ字":"TOYAMA KEN","市区町村コード":"16211","市区町村名":"射水市","市区町村名カナ":"イミズシ","市区町村名ローマ字":"IMIZU SHI","大字町丁目コード":"162110129000","大字町丁目名":"堀岡新明神","緯度":36.775021,"経度":137.112067},{"都道府県コード":"16","都道府県名":"富山県","都道府県名カナ":"トヤマケン","都道府県名ローマ字":"TOYAMA KEN","市区町村コード":"16211","市区町村名":"射水市","市区町村名カナ":"イミズシ","市区町村名ローマ字":"IMIZU SHI","大字町丁目コード":"162110130000","大字町丁目名":"堀岡古明神","緯度":36.769167,"経度":137.134316},{"都道府県コード":"16","都道府県名":"富山県","都道府県名カナ":"トヤマケン","都道府県名ローマ字":"TOYAMA KEN","市区町村コード":"16211","市区町村名":"射水市","市区町村名カナ":"イミズシ","市区町村名ローマ字":"IMIZU SHI","大字町丁目コード":"162110131000","大字町丁目名":"堀岡明神新","緯度":36.773027,"経度":137.119822},{"都道府県コード":"16","都道府県名":"富山県","都道府県名カナ":"トヤマケン","都道府県名ローマ字":"TOYAMA KEN","市区町村コード":"16211","市区町村名":"射水市","市区町村名カナ":"イミズシ","市区町村名ローマ字":"IMIZU SHI","大字町丁目コード":"162110132000","大字町丁目名":"堀内","緯度":36.714425,"経度":137.050206},{"都道府県コード":"16","都道府県名":"富山県","都道府県名カナ":"トヤマケン","都道府県名ローマ字":"TOYAMA KEN","市区町村コード":"16211","市区町村名":"射水市","市区町村名カナ":"イミズシ","市区町村名ローマ字":"IMIZU SHI","大字町丁目コード":"162110133000","大字町丁目名":"本開発","緯度":36.728786,"経度":137.082865},{"都道府県コード":"16","都道府県名":"富山県","都道府県名カナ":"トヤマケン","都道府県名ローマ字":"TOYAMA KEN","市区町村コード":"16211","市区町村名":"射水市","市区町村名カナ":"イミズシ","市区町村名ローマ字":"IMIZU SHI","大字町丁目コード":"162110134000","大字町丁目名":"本江","緯度":36.758345,"経度":137.172965},{"都道府県コード":"16","都道府県名":"富山県","都道府県名カナ":"トヤマケン","都道府県名ローマ字":"TOYAMA KEN","市区町村コード":"16211","市区町村名":"射水市","市区町村名カナ":"イミズシ","市区町村名ローマ字":"IMIZU SHI","大字町丁目コード":"162110135000","大字町丁目名":"本江北","緯度":36.754113,"経度":137.17102},{"都道府県コード":"16","都道府県名":"富山県","都道府県名カナ":"トヤマケン","都道府県名ローマ字":"TOYAMA KEN","市区町村コード":"16211","市区町村名":"射水市","市区町村名カナ":"イミズシ","市区町村名ローマ字":"IMIZU SHI","大字町丁目コード":"162110136000","大字町丁目名":"本江三箇","緯度":36.75954,"経度":137.170521},{"都道府県コード":"16","都道府県名":"富山県","都道府県名カナ":"トヤマケン","都道府県名ローマ字":"TOYAMA KEN","市区町村コード":"16211","市区町村名":"射水市","市区町村名カナ":"イミズシ","市区町村名ローマ字":"IMIZU SHI","大字町丁目コード":"162110137000","大字町丁目名":"本江利波","緯度":36.746071,"経度":137.167106},{"都道府県コード":"16","都道府県名":"富山県","都道府県名カナ":"トヤマケン","都道府県名ローマ字":"TOYAMA KEN","市区町村コード":"16211","市区町村名":"射水市","市区町村名カナ":"イミズシ","市区町村名ローマ字":"IMIZU SHI","大字町丁目コード":"162110138000","大字町丁目名":"本江中","緯度":36.748231,"経度":137.169513},{"都道府県コード":"16","都道府県名":"富山県","都道府県名カナ":"トヤマケン","都道府県名ローマ字":"TOYAMA KEN","市区町村コード":"16211","市区町村名":"射水市","市区町村名カナ":"イミズシ","市区町村名ローマ字":"IMIZU SHI","大字町丁目コード":"162110139000","大字町丁目名":"本江中新","緯度":36.753929,"経度":137.168442},{"都道府県コード":"16","都道府県名":"富山県","都道府県名カナ":"トヤマケン","都道府県名ローマ字":"TOYAMA KEN","市区町村コード":"16211","市区町村名":"射水市","市区町村名カナ":"イミズシ","市区町村名ローマ字":"IMIZU SHI","大字町丁目コード":"162110140000","大字町丁目名":"本江西","緯度":36.753281,"経度":137.165793},{"都道府県コード":"16","都道府県名":"富山県","都道府県名カナ":"トヤマケン","都道府県名ローマ字":"TOYAMA KEN","市区町村コード":"16211","市区町村名":"射水市","市区町村名カナ":"イミズシ","市区町村名ローマ字":"IMIZU SHI","大字町丁目コード":"162110141000","大字町丁目名":"本江針山","緯度":36.756298,"経度":137.163023},{"都道府県コード":"16","都道府県名":"富山県","都道府県名カナ":"トヤマケン","都道府県名ローマ字":"TOYAMA KEN","市区町村コード":"16211","市区町村名":"射水市","市区町村名カナ":"イミズシ","市区町村名ローマ字":"IMIZU SHI","大字町丁目コード":"162110142000","大字町丁目名":"本江針山新","緯度":36.757694,"経度":137.160269},{"都道府県コード":"16","都道府県名":"富山県","都道府県名カナ":"トヤマケン","都道府県名ローマ字":"TOYAMA KEN","市区町村コード":"16211","市区町村名":"射水市","市区町村名カナ":"イミズシ","市区町村名ローマ字":"IMIZU SHI","大字町丁目コード":"162110143000","大字町丁目名":"本江針山開","緯度":36.759086,"経度":137.163545},{"都道府県コード":"16","都道府県名":"富山県","都道府県名カナ":"トヤマケン","都道府県名ローマ字":"TOYAMA KEN","市区町村コード":"16211","市区町村名":"射水市","市区町村名カナ":"イミズシ","市区町村名ローマ字":"IMIZU SHI","大字町丁目コード":"162110144000","大字町丁目名":"本江東","緯度":36.752193,"経度":137.178353},{"都道府県コード":"16","都道府県名":"富山県","都道府県名カナ":"トヤマケン","都道府県名ローマ字":"TOYAMA KEN","市区町村コード":"16211","市区町村名":"射水市","市区町村名カナ":"イミズシ","市区町村名ローマ字":"IMIZU SHI","大字町丁目コード":"162110145000","大字町丁目名":"本江南","緯度":36.745087,"経度":137.16723},{"都道府県コード":"16","都道府県名":"富山県","都道府県名カナ":"トヤマケン","都道府県名ローマ字":"TOYAMA KEN","市区町村コード":"16211","市区町村名":"射水市","市区町村名カナ":"イミズシ","市区町村名ローマ字":"IMIZU SHI","大字町丁目コード":"162110146000","大字町丁目名":"本田","緯度":36.718412,"経度":137.07183},{"都道府県コード":"16","都道府県名":"富山県","都道府県名カナ":"トヤマケン","都道府県名ローマ字":"TOYAMA KEN","市区町村コード":"16211","市区町村名":"射水市","市区町村名カナ":"イミズシ","市区町村名ローマ字":"IMIZU SHI","大字町丁目コード":"162110147001","大字町丁目名":"本町一丁目","緯度":36.783698,"経度":137.076426},{"都道府県コード":"16","都道府県名":"富山県","都道府県名カナ":"トヤマケン","都道府県名ローマ字":"TOYAMA KEN","市区町村コード":"16211","市区町村名":"射水市","市区町村名カナ":"イミズシ","市区町村名ローマ字":"IMIZU SHI","大字町丁目コード":"162110147002","大字町丁目名":"本町二丁目","緯度":36.783051,"経度":137.079598},{"都道府県コード":"16","都道府県名":"富山県","都道府県名カナ":"トヤマケン","都道府県名ローマ字":"TOYAMA KEN","市区町村コード":"16211","市区町村名":"射水市","市区町村名カナ":"イミズシ","市区町村名ローマ字":"IMIZU SHI","大字町丁目コード":"162110147003","大字町丁目名":"本町三丁目","緯度":36.781917,"経度":137.081947},{"都道府県コード":"16","都道府県名":"富山県","都道府県名カナ":"トヤマケン","都道府県名ローマ字":"TOYAMA KEN","市区町村コード":"16211","市区町村名":"射水市","市区町村名カナ":"イミズシ","市区町村名ローマ字":"IMIZU SHI","大字町丁目コード":"162110148000","大字町丁目名":"松木","緯度":36.761477,"経度":137.06992},{"都道府県コード":"16","都道府県名":"富山県","都道府県名カナ":"トヤマケン","都道府県名ローマ字":"TOYAMA KEN","市区町村コード":"16211","市区町村名":"射水市","市区町村名カナ":"イミズシ","市区町村名ローマ字":"IMIZU SHI","大字町丁目コード":"162110149000","大字町丁目名":"三日曽根","緯度":36.778922,"経度":137.079719},{"都道府県コード":"16","都道府県名":"富山県","都道府県名カナ":"トヤマケン","都道府県名ローマ字":"TOYAMA KEN","市区町村コード":"16211","市区町村名":"射水市","市区町村名カナ":"イミズシ","市区町村名ローマ字":"IMIZU SHI","大字町丁目コード":"162110150000","大字町丁目名":"水戸田","緯度":36.707442,"経度":137.071885},{"都道府県コード":"16","都道府県名":"富山県","都道府県名カナ":"トヤマケン","都道府県名ローマ字":"TOYAMA KEN","市区町村コード":"16211","市区町村名":"射水市","市区町村名カナ":"イミズシ","市区町村名ローマ字":"IMIZU SHI","大字町丁目コード":"162110151000","大字町丁目名":"緑町","緯度":36.775036,"経度":137.081535},{"都道府県コード":"16","都道府県名":"富山県","都道府県名カナ":"トヤマケン","都道府県名ローマ字":"TOYAMA KEN","市区町村コード":"16211","市区町村名":"射水市","市区町村名カナ":"イミズシ","市区町村名ローマ字":"IMIZU SHI","大字町丁目コード":"162110152000","大字町丁目名":"港町","緯度":36.786868,"経度":137.077598},{"都道府県コード":"16","都道府県名":"富山県","都道府県名カナ":"トヤマケン","都道府県名ローマ字":"TOYAMA KEN","市区町村コード":"16211","市区町村名":"射水市","市区町村名カナ":"イミズシ","市区町村名ローマ字":"IMIZU SHI","大字町丁目コード":"162110153001","大字町丁目名":"南太閤山一丁目","緯度":36.699551,"経度":137.097164},{"都道府県コード":"16","都道府県名":"富山県","都道府県名カナ":"トヤマケン","都道府県名ローマ字":"TOYAMA KEN","市区町村コード":"16211","市区町村名":"射水市","市区町村名カナ":"イミズシ","市区町村名ローマ字":"IMIZU SHI","大字町丁目コード":"162110153002","大字町丁目名":"南太閤山二丁目","緯度":36.698841,"経度":137.093533},{"都道府県コード":"16","都道府県名":"富山県","都道府県名カナ":"トヤマケン","都道府県名ローマ字":"TOYAMA KEN","市区町村コード":"16211","市区町村名":"射水市","市区町村名カナ":"イミズシ","市区町村名ローマ字":"IMIZU SHI","大字町丁目コード":"162110153003","大字町丁目名":"南太閤山三丁目","緯度":36.69844,"経度":137.091362},{"都道府県コード":"16","都道府県名":"富山県","都道府県名カナ":"トヤマケン","都道府県名ローマ字":"TOYAMA KEN","市区町村コード":"16211","市区町村名":"射水市","市区町村名カナ":"イミズシ","市区町村名ローマ字":"IMIZU SHI","大字町丁目コード":"162110153004","大字町丁目名":"南太閤山四丁目","緯度":36.697593,"経度":137.090006},{"都道府県コード":"16","都道府県名":"富山県","都道府県名カナ":"トヤマケン","都道府県名ローマ字":"TOYAMA KEN","市区町村コード":"16211","市区町村名":"射水市","市区町村名カナ":"イミズシ","市区町村名ローマ字":"IMIZU SHI","大字町丁目コード":"162110153005","大字町丁目名":"南太閤山五丁目","緯度":36.697587,"経度":137.088304},{"都道府県コード":"16","都道府県名":"富山県","都道府県名カナ":"トヤマケン","都道府県名ローマ字":"TOYAMA KEN","市区町村コード":"16211","市区町村名":"射水市","市区町村名カナ":"イミズシ","市区町村名ローマ字":"IMIZU SHI","大字町丁目コード":"162110153006","大字町丁目名":"南太閤山六丁目","緯度":36.697781,"経度":137.086902},{"都道府県コード":"16","都道府県名":"富山県","都道府県名カナ":"トヤマケン","都道府県名ローマ字":"TOYAMA KEN","市区町村コード":"16211","市区町村名":"射水市","市区町村名カナ":"イミズシ","市区町村名ローマ字":"IMIZU SHI","大字町丁目コード":"162110153007","大字町丁目名":"南太閤山七丁目","緯度":36.699425,"経度":137.08257},{"都道府県コード":"16","都道府県名":"富山県","都道府県名カナ":"トヤマケン","都道府県名ローマ字":"TOYAMA KEN","市区町村コード":"16211","市区町村名":"射水市","市区町村名カナ":"イミズシ","市区町村名ローマ字":"IMIZU SHI","大字町丁目コード":"162110153008","大字町丁目名":"南太閤山八丁目","緯度":36.696241,"経度":137.088692},{"都道府県コード":"16","都道府県名":"富山県","都道府県名カナ":"トヤマケン","都道府県名ローマ字":"TOYAMA KEN","市区町村コード":"16211","市区町村名":"射水市","市区町村名カナ":"イミズシ","市区町村名ローマ字":"IMIZU SHI","大字町丁目コード":"162110153009","大字町丁目名":"南太閤山九丁目","緯度":36.69518,"経度":137.094803},{"都道府県コード":"16","都道府県名":"富山県","都道府県名カナ":"トヤマケン","都道府県名ローマ字":"TOYAMA KEN","市区町村コード":"16211","市区町村名":"射水市","市区町村名カナ":"イミズシ","市区町村名ローマ字":"IMIZU SHI","大字町丁目コード":"162110153010","大字町丁目名":"南太閤山十丁目","緯度":36.69686,"経度":137.092052},{"都道府県コード":"16","都道府県名":"富山県","都道府県名カナ":"トヤマケン","都道府県名ローマ字":"TOYAMA KEN","市区町村コード":"16211","市区町村名":"射水市","市区町村名カナ":"イミズシ","市区町村名ローマ字":"IMIZU SHI","大字町丁目コード":"162110153011","大字町丁目名":"南太閤山十一丁目","緯度":36.696985,"経度":137.094147},{"都道府県コード":"16","都道府県名":"富山県","都道府県名カナ":"トヤマケン","都道府県名ローマ字":"TOYAMA KEN","市区町村コード":"16211","市区町村名":"射水市","市区町村名カナ":"イミズシ","市区町村名ローマ字":"IMIZU SHI","大字町丁目コード":"162110153012","大字町丁目名":"南太閤山十二丁目","緯度":36.696973,"経度":137.096217},{"都道府県コード":"16","都道府県名":"富山県","都道府県名カナ":"トヤマケン","都道府県名ローマ字":"TOYAMA KEN","市区町村コード":"16211","市区町村名":"射水市","市区町村名カナ":"イミズシ","市区町村名ローマ字":"IMIZU SHI","大字町丁目コード":"162110153013","大字町丁目名":"南太閤山十三丁目","緯度":36.697609,"経度":137.097523},{"都道府県コード":"16","都道府県名":"富山県","都道府県名カナ":"トヤマケン","都道府県名ローマ字":"TOYAMA KEN","市区町村コード":"16211","市区町村名":"射水市","市区町村名カナ":"イミズシ","市区町村名ローマ字":"IMIZU SHI","大字町丁目コード":"162110153014","大字町丁目名":"南太閤山十四丁目","緯度":36.698289,"経度":137.098545},{"都道府県コード":"16","都道府県名":"富山県","都道府県名カナ":"トヤマケン","都道府県名ローマ字":"TOYAMA KEN","市区町村コード":"16211","市区町村名":"射水市","市区町村名カナ":"イミズシ","市区町村名ローマ字":"IMIZU SHI","大字町丁目コード":"162110153015","大字町丁目名":"南太閤山十五丁目","緯度":36.696397,"経度":137.099195},{"都道府県コード":"16","都道府県名":"富山県","都道府県名カナ":"トヤマケン","都道府県名ローマ字":"TOYAMA KEN","市区町村コード":"16211","市区町村名":"射水市","市区町村名カナ":"イミズシ","市区町村名ローマ字":"IMIZU SHI","大字町丁目コード":"162110153016","大字町丁目名":"南太閤山十六丁目","緯度":36.694417,"経度":137.097218},{"都道府県コード":"16","都道府県名":"富山県","都道府県名カナ":"トヤマケン","都道府県名ローマ字":"TOYAMA KEN","市区町村コード":"16211","市区町村名":"射水市","市区町村名カナ":"イミズシ","市区町村名ローマ字":"IMIZU SHI","大字町丁目コード":"162110153017","大字町丁目名":"南太閤山十七丁目","緯度":36.694845,"経度":137.09347},{"都道府県コード":"16","都道府県名":"富山県","都道府県名カナ":"トヤマケン","都道府県名ローマ字":"TOYAMA KEN","市区町村コード":"16211","市区町村名":"射水市","市区町村名カナ":"イミズシ","市区町村名ローマ字":"IMIZU SHI","大字町丁目コード":"162110153018","大字町丁目名":"南太閤山十八丁目","緯度":36.695695,"経度":137.088474},{"都道府県コード":"16","都道府県名":"富山県","都道府県名カナ":"トヤマケン","都道府県名ローマ字":"TOYAMA KEN","市区町村コード":"16211","市区町村名":"射水市","市区町村名カナ":"イミズシ","市区町村名ローマ字":"IMIZU SHI","大字町丁目コード":"162110153019","大字町丁目名":"南太閤山十九丁目","緯度":36.695566,"経度":137.084793},{"都道府県コード":"16","都道府県名":"富山県","都道府県名カナ":"トヤマケン","都道府県名ローマ字":"TOYAMA KEN","市区町村コード":"16211","市区町村名":"射水市","市区町村名カナ":"イミズシ","市区町村名ローマ字":"IMIZU SHI","大字町丁目コード":"162110154000","大字町丁目名":"南高木","緯度":36.739202,"経度":137.07408},{"都道府県コード":"16","都道府県名":"富山県","都道府県名カナ":"トヤマケン","都道府県名ローマ字":"TOYAMA KEN","市区町村コード":"16211","市区町村名":"射水市","市区町村名カナ":"イミズシ","市区町村名ローマ字":"IMIZU SHI","大字町丁目コード":"162110155000","大字町丁目名":"八島","緯度":36.755582,"経度":137.149791},{"都道府県コード":"16","都道府県名":"富山県","都道府県名カナ":"トヤマケン","都道府県名ローマ字":"TOYAMA KEN","市区町村コード":"16211","市区町村名":"射水市","市区町村名カナ":"イミズシ","市区町村名ローマ字":"IMIZU SHI","大字町丁目コード":"162110156000","大字町丁目名":"安吉","緯度":36.721464,"経度":137.068272},{"都道府県コード":"16","都道府県名":"富山県","都道府県名カナ":"トヤマケン","都道府県名ローマ字":"TOYAMA KEN","市区町村コード":"16211","市区町村名":"射水市","市区町村名カナ":"イミズシ","市区町村名ローマ字":"IMIZU SHI","大字町丁目コード":"162110157000","大字町丁目名":"八塚","緯度":36.729236,"経度":137.059349},{"都道府県コード":"16","都道府県名":"富山県","都道府県名カナ":"トヤマケン","都道府県名ローマ字":"TOYAMA KEN","市区町村コード":"16211","市区町村名":"射水市","市区町村名カナ":"イミズシ","市区町村名ローマ字":"IMIZU SHI","大字町丁目コード":"162110158000","大字町丁目名":"山本","緯度":36.684059,"経度":137.104621},{"都道府県コード":"16","都道府県名":"富山県","都道府県名カナ":"トヤマケン","都道府県名ローマ字":"TOYAMA KEN","市区町村コード":"16211","市区町村名":"射水市","市区町村名カナ":"イミズシ","市区町村名ローマ字":"IMIZU SHI","大字町丁目コード":"162110159000","大字町丁目名":"山本新","緯度":36.687712,"経度":137.111993},{"都道府県コード":"16","都道府県名":"富山県","都道府県名カナ":"トヤマケン","都道府県名ローマ字":"TOYAMA KEN","市区町村コード":"16211","市区町村名":"射水市","市区町村名カナ":"イミズシ","市区町村名ローマ字":"IMIZU SHI","大字町丁目コード":"162110160000","大字町丁目名":"山屋","緯度":36.751203,"経度":137.160019},{"都道府県コード":"16","都道府県名":"富山県","都道府県名カナ":"トヤマケン","都道府県名ローマ字":"TOYAMA KEN","市区町村コード":"16211","市区町村名":"射水市","市区町村名カナ":"イミズシ","市区町村名ローマ字":"IMIZU SHI","大字町丁目コード":"162110161001","大字町丁目名":"流通センター青井谷一丁目","緯度":36.694464,"経度":137.065447},{"都道府県コード":"16","都道府県名":"富山県","都道府県名カナ":"トヤマケン","都道府県名ローマ字":"TOYAMA KEN","市区町村コード":"16211","市区町村名":"射水市","市区町村名カナ":"イミズシ","市区町村名ローマ字":"IMIZU SHI","大字町丁目コード":"162110161002","大字町丁目名":"流通センター青井谷二丁目","緯度":36.696185,"経度":137.070275},{"都道府県コード":"16","都道府県名":"富山県","都道府県名カナ":"トヤマケン","都道府県名ローマ字":"TOYAMA KEN","市区町村コード":"16211","市区町村名":"射水市","市区町村名カナ":"イミズシ","市区町村名ローマ字":"IMIZU SHI","大字町丁目コード":"162110162001","大字町丁目名":"流通センター下条一丁目","緯度":36.69844,"経度":137.071844},{"都道府県コード":"16","都道府県名":"富山県","都道府県名カナ":"トヤマケン","都道府県名ローマ字":"TOYAMA KEN","市区町村コード":"16211","市区町村名":"射水市","市区町村名カナ":"イミズシ","市区町村名ローマ字":"IMIZU SHI","大字町丁目コード":"162110163002","大字町丁目名":"流通センター水戸田二丁目","緯度":36.697954,"経度":137.066085},{"都道府県コード":"16","都道府県名":"富山県","都道府県名カナ":"トヤマケン","都道府県名ローマ字":"TOYAMA KEN","市区町村コード":"16211","市区町村名":"射水市","市区町村名カナ":"イミズシ","市区町村名ローマ字":"IMIZU SHI","大字町丁目コード":"162110163003","大字町丁目名":"流通センター水戸田三丁目","緯度":36.698831,"経度":137.069149},{"都道府県コード":"16","都道府県名":"富山県","都道府県名カナ":"トヤマケン","都道府県名ローマ字":"TOYAMA KEN","市区町村コード":"16211","市区町村名":"射水市","市区町村名カナ":"イミズシ","市区町村名ローマ字":"IMIZU SHI","大字町丁目コード":"162110164000","大字町丁目名":"若杉","緯度":36.744253,"経度":137.055577},{"都道府県コード":"16","都道府県名":"富山県","都道府県名カナ":"トヤマケン","都道府県名ローマ字":"TOYAMA KEN","市区町村コード":"16211","市区町村名":"射水市","市区町村名カナ":"イミズシ","市区町村名ローマ字":"IMIZU SHI","大字町丁目コード":"162110165000","大字町丁目名":"若林","緯度":36.710864,"経度":137.065199},{"都道府県コード":"16","都道府県名":"富山県","都道府県名カナ":"トヤマケン","都道府県名ローマ字":"TOYAMA KEN","市区町村コード":"16211","市区町村名":"射水市","市区町村名カナ":"イミズシ","市区町村名ローマ字":"IMIZU SHI","大字町丁目コード":"162110166000","大字町丁目名":"鷲塚","緯度":36.72133,"経度":137.125007},{"都道府県コード":"16","都道府県名":"富山県","都道府県名カナ":"トヤマケン","都道府県名ローマ字":"TOYAMA KEN","市区町村コード":"16211","市区町村名":"射水市","市区町村名カナ":"イミズシ","市区町村名ローマ字":"IMIZU SHI","大字町丁目コード":"162110167000","大字町丁目名":"作道","緯度":36.755717,"経度":137.09028},{"都道府県コード":"16","都道府県名":"富山県","都道府県名カナ":"トヤマケン","都道府県名ローマ字":"TOYAMA KEN","市区町村コード":"16211","市区町村名":"射水市","市区町村名カナ":"イミズシ","市区町村名ローマ字":"IMIZU SHI","大字町丁目コード":"162110168000","大字町丁目名":"神楽町","緯度":36.760913,"経度":137.083243},{"都道府県コード":"16","都道府県名":"富山県","都道府県名カナ":"トヤマケン","都道府県名ローマ字":"TOYAMA KEN","市区町村コード":"16211","市区町村名":"射水市","市区町村名カナ":"イミズシ","市区町村名ローマ字":"IMIZU SHI","大字町丁目コード":"162110169000","大字町丁目名":"川口宮袋入会地","緯度":36.765857,"経度":137.051499},{"都道府県コード":"16","都道府県名":"富山県","都道府県名カナ":"トヤマケン","都道府県名ローマ字":"TOYAMA KEN","市区町村コード":"16211","市区町村名":"射水市","市区町村名カナ":"イミズシ","市区町村名ローマ字":"IMIZU SHI","大字町丁目コード":"162110170000","大字町丁目名":"串田","緯度":36.691829,"経度":137.042553},{"都道府県コード":"16","都道府県名":"富山県","都道府県名カナ":"トヤマケン","都道府県名ローマ字":"TOYAMA KEN","市区町村コード":"16211","市区町村名":"射水市","市区町村名カナ":"イミズシ","市区町村名ローマ字":"IMIZU SHI","大字町丁目コード":"162110171000","大字町丁目名":"生源寺新","緯度":36.689406,"経度":137.045793},{"都道府県コード":"16","都道府県名":"富山県","都道府県名カナ":"トヤマケン","都道府県名ローマ字":"TOYAMA KEN","市区町村コード":"16211","市区町村名":"射水市","市区町村名カナ":"イミズシ","市区町村名ローマ字":"IMIZU SHI","大字町丁目コード":"162110172000","大字町丁目名":"上野","緯度":36.692531,"経度":137.084005},{"都道府県コード":"16","都道府県名":"富山県","都道府県名カナ":"トヤマケン","都道府県名ローマ字":"TOYAMA KEN","市区町村コード":"16211","市区町村名":"射水市","市区町村名カナ":"イミズシ","市区町村名ローマ字":"IMIZU SHI","大字町丁目コード":"162110173000","大字町丁目名":"入会地","緯度":36.675591,"経度":137.08325},{"都道府県コード":"16","都道府県名":"富山県","都道府県名カナ":"トヤマケン","都道府県名ローマ字":"TOYAMA KEN","市区町村コード":"16211","市区町村名":"射水市","市区町村名カナ":"イミズシ","市区町村名ローマ字":"IMIZU SHI","大字町丁目コード":"162110174000","大字町丁目名":"上条","緯度":36.712009,"経度":137.032286},{"都道府県コード":"16","都道府県名":"富山県","都道府県名カナ":"トヤマケン","都道府県名ローマ字":"TOYAMA KEN","市区町村コード":"16211","市区町村名":"射水市","市区町村名カナ":"イミズシ","市区町村名ローマ字":"IMIZU SHI","大字町丁目コード":"162110175000","大字町丁目名":"土合","緯度":36.722752,"経度":137.039161}]