[{"都道府県コード":"40","都道府県名":"福岡県","都道府県名カナ":"フクオカケン","都道府県名ローマ字":"FUKUOKA KEN","市区町村コード":"40447","市区町村名":"朝倉郡筑前町","市区町村名カナ":"アサクラグンチクゼンマチ","市区町村名ローマ字":"ASAKURA GUN CHIKUZEN MACHI","大字町丁目コード":"404470001000","大字町丁目名":"赤坂","緯度":33.480188,"経度":130.589599},{"都道府県コード":"40","都道府県名":"福岡県","都道府県名カナ":"フクオカケン","都道府県名ローマ字":"FUKUOKA KEN","市区町村コード":"40447","市区町村名":"朝倉郡筑前町","市区町村名カナ":"アサクラグンチクゼンマチ","市区町村名ローマ字":"ASAKURA GUN CHIKUZEN MACHI","大字町丁目コード":"404470002000","大字町丁目名":"朝園","緯度":33.426049,"経度":130.635384},{"都道府県コード":"40","都道府県名":"福岡県","都道府県名カナ":"フクオカケン","都道府県名ローマ字":"FUKUOKA KEN","市区町村コード":"40447","市区町村名":"朝倉郡筑前町","市区町村名カナ":"アサクラグンチクゼンマチ","市区町村名ローマ字":"ASAKURA GUN CHIKUZEN MACHI","大字町丁目コード":"404470003000","大字町丁目名":"朝日","緯度":33.466769,"経度":130.566979},{"都道府県コード":"40","都道府県名":"福岡県","都道府県名カナ":"フクオカケン","都道府県名ローマ字":"FUKUOKA KEN","市区町村コード":"40447","市区町村名":"朝倉郡筑前町","市区町村名カナ":"アサクラグンチクゼンマチ","市区町村名ローマ字":"ASAKURA GUN CHIKUZEN MACHI","大字町丁目コード":"404470004000","大字町丁目名":"石櫃","緯度":33.465286,"経度":130.580915},{"都道府県コード":"40","都道府県名":"福岡県","都道府県名カナ":"フクオカケン","都道府県名ローマ字":"FUKUOKA KEN","市区町村コード":"40447","市区町村名":"朝倉郡筑前町","市区町村名カナ":"アサクラグンチクゼンマチ","市区町村名ローマ字":"ASAKURA GUN CHIKUZEN MACHI","大字町丁目コード":"404470005000","大字町丁目名":"弥永","緯度":33.442405,"経度":130.649567},{"都道府県コード":"40","都道府県名":"福岡県","都道府県名カナ":"フクオカケン","都道府県名ローマ字":"FUKUOKA KEN","市区町村コード":"40447","市区町村名":"朝倉郡筑前町","市区町村名カナ":"アサクラグンチクゼンマチ","市区町村名ローマ字":"ASAKURA GUN CHIKUZEN MACHI","大字町丁目コード":"404470006000","大字町丁目名":"大久保","緯度":33.429975,"経度":130.613421},{"都道府県コード":"40","都道府県名":"福岡県","都道府県名カナ":"フクオカケン","都道府県名ローマ字":"FUKUOKA KEN","市区町村コード":"40447","市区町村名":"朝倉郡筑前町","市区町村名カナ":"アサクラグンチクゼンマチ","市区町村名ローマ字":"ASAKURA GUN CHIKUZEN MACHI","大字町丁目コード":"404470007000","大字町丁目名":"大塚","緯度":33.435008,"経度":130.653425},{"都道府県コード":"40","都道府県名":"福岡県","都道府県名カナ":"フクオカケン","都道府県名ローマ字":"FUKUOKA KEN","市区町村コード":"40447","市区町村名":"朝倉郡筑前町","市区町村名カナ":"アサクラグンチクゼンマチ","市区町村名ローマ字":"ASAKURA GUN CHIKUZEN MACHI","大字町丁目コード":"404470008000","大字町丁目名":"上高場","緯度":33.437291,"経度":130.619674},{"都道府県コード":"40","都道府県名":"福岡県","都道府県名カナ":"フクオカケン","都道府県名ローマ字":"FUKUOKA KEN","市区町村コード":"40447","市区町村名":"朝倉郡筑前町","市区町村名カナ":"アサクラグンチクゼンマチ","市区町村名ローマ字":"ASAKURA GUN CHIKUZEN MACHI","大字町丁目コード":"404470009000","大字町丁目名":"櫛木","緯度":33.499582,"経度":130.660591},{"都道府県コード":"40","都道府県名":"福岡県","都道府県名カナ":"フクオカケン","都道府県名ローマ字":"FUKUOKA KEN","市区町村コード":"40447","市区町村名":"朝倉郡筑前町","市区町村名カナ":"アサクラグンチクゼンマチ","市区町村名ローマ字":"ASAKURA GUN CHIKUZEN MACHI","大字町丁目コード":"404470010000","大字町丁目名":"栗田","緯度":33.453848,"経度":130.636006},{"都道府県コード":"40","都道府県名":"福岡県","都道府県名カナ":"フクオカケン","都道府県名ローマ字":"FUKUOKA KEN","市区町村コード":"40447","市区町村名":"朝倉郡筑前町","市区町村名カナ":"アサクラグンチクゼンマチ","市区町村名ローマ字":"ASAKURA GUN CHIKUZEN MACHI","大字町丁目コード":"404470011000","大字町丁目名":"三箇山","緯度":33.488374,"経度":130.647857},{"都道府県コード":"40","都道府県名":"福岡県","都道府県名カナ":"フクオカケン","都道府県名ローマ字":"FUKUOKA KEN","市区町村コード":"40447","市区町村名":"朝倉郡筑前町","市区町村名カナ":"アサクラグンチクゼンマチ","市区町村名ローマ字":"ASAKURA GUN CHIKUZEN MACHI","大字町丁目コード":"404470012000","大字町丁目名":"四三嶋","緯度":33.432575,"経度":130.592451},{"都道府県コード":"40","都道府県名":"福岡県","都道府県名カナ":"フクオカケン","都道府県名ローマ字":"FUKUOKA KEN","市区町村コード":"40447","市区町村名":"朝倉郡筑前町","市区町村名カナ":"アサクラグンチクゼンマチ","市区町村名ローマ字":"ASAKURA GUN CHIKUZEN MACHI","大字町丁目コード":"404470013000","大字町丁目名":"篠隈","緯度":33.457824,"経度":130.600221},{"都道府県コード":"40","都道府県名":"福岡県","都道府県名カナ":"フクオカケン","都道府県名ローマ字":"FUKUOKA KEN","市区町村コード":"40447","市区町村名":"朝倉郡筑前町","市区町村名カナ":"アサクラグンチクゼンマチ","市区町村名ローマ字":"ASAKURA GUN CHIKUZEN MACHI","大字町丁目コード":"404470014000","大字町丁目名":"下高場","緯度":33.440834,"経度":130.604669},{"都道府県コード":"40","都道府県名":"福岡県","都道府県名カナ":"フクオカケン","都道府県名ローマ字":"FUKUOKA KEN","市区町村コード":"40447","市区町村名":"朝倉郡筑前町","市区町村名カナ":"アサクラグンチクゼンマチ","市区町村名ローマ字":"ASAKURA GUN CHIKUZEN MACHI","大字町丁目コード":"404470015000","大字町丁目名":"新町","緯度":33.43368,"経度":130.638157},{"都道府県コード":"40","都道府県名":"福岡県","都道府県名カナ":"フクオカケン","都道府県名ローマ字":"FUKUOKA KEN","市区町村コード":"40447","市区町村名":"朝倉郡筑前町","市区町村名カナ":"アサクラグンチクゼンマチ","市区町村名ローマ字":"ASAKURA GUN CHIKUZEN MACHI","大字町丁目コード":"404470016000","大字町丁目名":"曽根田","緯度":33.482357,"経度":130.614448},{"都道府県コード":"40","都道府県名":"福岡県","都道府県名カナ":"フクオカケン","都道府県名ローマ字":"FUKUOKA KEN","市区町村コード":"40447","市区町村名":"朝倉郡筑前町","市区町村名カナ":"アサクラグンチクゼンマチ","市区町村名ローマ字":"ASAKURA GUN CHIKUZEN MACHI","大字町丁目コード":"404470017000","大字町丁目名":"高田","緯度":33.419065,"経度":130.630201},{"都道府県コード":"40","都道府県名":"福岡県","都道府県名カナ":"フクオカケン","都道府県名ローマ字":"FUKUOKA KEN","市区町村コード":"40447","市区町村名":"朝倉郡筑前町","市区町村名カナ":"アサクラグンチクゼンマチ","市区町村名ローマ字":"ASAKURA GUN CHIKUZEN MACHI","大字町丁目コード":"404470018000","大字町丁目名":"高上","緯度":33.426716,"経度":130.620295},{"都道府県コード":"40","都道府県名":"福岡県","都道府県名カナ":"フクオカケン","都道府県名ローマ字":"FUKUOKA KEN","市区町村コード":"40447","市区町村名":"朝倉郡筑前町","市区町村名カナ":"アサクラグンチクゼンマチ","市区町村名ローマ字":"ASAKURA GUN CHIKUZEN MACHI","大字町丁目コード":"404470019000","大字町丁目名":"長者町","緯度":33.45427,"経度":130.609547},{"都道府県コード":"40","都道府県名":"福岡県","都道府県名カナ":"フクオカケン","都道府県名ローマ字":"FUKUOKA KEN","市区町村コード":"40447","市区町村名":"朝倉郡筑前町","市区町村名カナ":"アサクラグンチクゼンマチ","市区町村名ローマ字":"ASAKURA GUN CHIKUZEN MACHI","大字町丁目コード":"404470020000","大字町丁目名":"当所","緯度":33.451244,"経度":130.618309},{"都道府県コード":"40","都道府県名":"福岡県","都道府県名カナ":"フクオカケン","都道府県名ローマ字":"FUKUOKA KEN","市区町村コード":"40447","市区町村名":"朝倉郡筑前町","市区町村名カナ":"アサクラグンチクゼンマチ","市区町村名ローマ字":"ASAKURA GUN CHIKUZEN MACHI","大字町丁目コード":"404470021000","大字町丁目名":"砥上","緯度":33.478756,"経度":130.600043},{"都道府県コード":"40","都道府県名":"福岡県","都道府県名カナ":"フクオカケン","都道府県名ローマ字":"FUKUOKA KEN","市区町村コード":"40447","市区町村名":"朝倉郡筑前町","市区町村名カナ":"アサクラグンチクゼンマチ","市区町村名ローマ字":"ASAKURA GUN CHIKUZEN MACHI","大字町丁目コード":"404470022000","大字町丁目名":"中牟田","緯度":33.466618,"経度":130.575483},{"都道府県コード":"40","都道府県名":"福岡県","都道府県名カナ":"フクオカケン","都道府県名ローマ字":"FUKUOKA KEN","市区町村コード":"40447","市区町村名":"朝倉郡筑前町","市区町村名カナ":"アサクラグンチクゼンマチ","市区町村名ローマ字":"ASAKURA GUN CHIKUZEN MACHI","大字町丁目コード":"404470023000","大字町丁目名":"野町","緯度":33.423152,"経度":130.62361},{"都道府県コード":"40","都道府県名":"福岡県","都道府県名カナ":"フクオカケン","都道府県名ローマ字":"FUKUOKA KEN","市区町村コード":"40447","市区町村名":"朝倉郡筑前町","市区町村名カナ":"アサクラグンチクゼンマチ","市区町村名ローマ字":"ASAKURA GUN CHIKUZEN MACHI","大字町丁目コード":"404470024000","大字町丁目名":"畑嶋","緯度":33.462333,"経度":130.629801},{"都道府県コード":"40","都道府県名":"福岡県","都道府県名カナ":"フクオカケン","都道府県名ローマ字":"FUKUOKA KEN","市区町村コード":"40447","市区町村名":"朝倉郡筑前町","市区町村名カナ":"アサクラグンチクゼンマチ","市区町村名ローマ字":"ASAKURA GUN CHIKUZEN MACHI","大字町丁目コード":"404470025000","大字町丁目名":"原地蔵","緯度":33.409459,"経度":130.616381},{"都道府県コード":"40","都道府県名":"福岡県","都道府県名カナ":"フクオカケン","都道府県名ローマ字":"FUKUOKA KEN","市区町村コード":"40447","市区町村名":"朝倉郡筑前町","市区町村名カナ":"アサクラグンチクゼンマチ","市区町村名ローマ字":"ASAKURA GUN CHIKUZEN MACHI","大字町丁目コード":"404470026000","大字町丁目名":"東小田","緯度":33.451421,"経度":130.57931},{"都道府県コード":"40","都道府県名":"福岡県","都道府県名カナ":"フクオカケン","都道府県名ローマ字":"FUKUOKA KEN","市区町村コード":"40447","市区町村名":"朝倉郡筑前町","市区町村名カナ":"アサクラグンチクゼンマチ","市区町村名ローマ字":"ASAKURA GUN CHIKUZEN MACHI","大字町丁目コード":"404470027000","大字町丁目名":"久光","緯度":33.438994,"経度":130.634828},{"都道府県コード":"40","都道府県名":"福岡県","都道府県名カナ":"フクオカケン","都道府県名ローマ字":"FUKUOKA KEN","市区町村コード":"40447","市区町村名":"朝倉郡筑前町","市区町村名カナ":"アサクラグンチクゼンマチ","市区町村名ローマ字":"ASAKURA GUN CHIKUZEN MACHI","大字町丁目コード":"404470028000","大字町丁目名":"吹田","緯度":33.470836,"経度":130.590266},{"都道府県コード":"40","都道府県名":"福岡県","都道府県名カナ":"フクオカケン","都道府県名ローマ字":"FUKUOKA KEN","市区町村コード":"40447","市区町村名":"朝倉郡筑前町","市区町村名カナ":"アサクラグンチクゼンマチ","市区町村名ローマ字":"ASAKURA GUN CHIKUZEN MACHI","大字町丁目コード":"404470029000","大字町丁目名":"二","緯度":33.476485,"経度":130.564312},{"都道府県コード":"40","都道府県名":"福岡県","都道府県名カナ":"フクオカケン","都道府県名ローマ字":"FUKUOKA KEN","市区町村コード":"40447","市区町村名":"朝倉郡筑前町","市区町村名カナ":"アサクラグンチクゼンマチ","市区町村名ローマ字":"ASAKURA GUN CHIKUZEN MACHI","大字町丁目コード":"404470030000","大字町丁目名":"松延","緯度":33.463259,"経度":130.587469},{"都道府県コード":"40","都道府県名":"福岡県","都道府県名カナ":"フクオカケン","都道府県名ローマ字":"FUKUOKA KEN","市区町村コード":"40447","市区町村名":"朝倉郡筑前町","市区町村名カナ":"アサクラグンチクゼンマチ","市区町村名ローマ字":"ASAKURA GUN CHIKUZEN MACHI","大字町丁目コード":"404470031000","大字町丁目名":"三並","緯度":33.474469,"経度":130.625972},{"都道府県コード":"40","都道府県名":"福岡県","都道府県名カナ":"フクオカケン","都道府県名ローマ字":"FUKUOKA KEN","市区町村コード":"40447","市区町村名":"朝倉郡筑前町","市区町村名カナ":"アサクラグンチクゼンマチ","市区町村名ローマ字":"ASAKURA GUN CHIKUZEN MACHI","大字町丁目コード":"404470032000","大字町丁目名":"三牟田","緯度":33.472773,"経度":130.607045},{"都道府県コード":"40","都道府県名":"福岡県","都道府県名カナ":"フクオカケン","都道府県名ローマ字":"FUKUOKA KEN","市区町村コード":"40447","市区町村名":"朝倉郡筑前町","市区町村名カナ":"アサクラグンチクゼンマチ","市区町村名ローマ字":"ASAKURA GUN CHIKUZEN MACHI","大字町丁目コード":"404470033000","大字町丁目名":"森山","緯度":33.455747,"経度":130.629721},{"都道府県コード":"40","都道府県名":"福岡県","都道府県名カナ":"フクオカケン","都道府県名ローマ字":"FUKUOKA KEN","市区町村コード":"40447","市区町村名":"朝倉郡筑前町","市区町村名カナ":"アサクラグンチクゼンマチ","市区町村名ローマ字":"ASAKURA GUN CHIKUZEN MACHI","大字町丁目コード":"404470034000","大字町丁目名":"安野","緯度":33.443417,"経度":130.595108},{"都道府県コード":"40","都道府県名":"福岡県","都道府県名カナ":"フクオカケン","都道府県名ローマ字":"FUKUOKA KEN","市区町村コード":"40447","市区町村名":"朝倉郡筑前町","市区町村名カナ":"アサクラグンチクゼンマチ","市区町村名ローマ字":"ASAKURA GUN CHIKUZEN MACHI","大字町丁目コード":"404470035000","大字町丁目名":"山隈","緯度":33.420314,"経度":130.609787},{"都道府県コード":"40","都道府県名":"福岡県","都道府県名カナ":"フクオカケン","都道府県名ローマ字":"FUKUOKA KEN","市区町村コード":"40447","市区町村名":"朝倉郡筑前町","市区町村名カナ":"アサクラグンチクゼンマチ","市区町村名ローマ字":"ASAKURA GUN CHIKUZEN MACHI","大字町丁目コード":"404470036000","大字町丁目名":"依井","緯度":33.429917,"経度":130.643468}]