[{"都道府県コード":"06","都道府県名":"山形県","都道府県名カナ":"ヤマガタケン","都道府県名ローマ字":"YAMAGATA KEN","市区町村コード":"06362","市区町村名":"最上郡最上町","市区町村名カナ":"モガミグンモガミマチ","市区町村名ローマ字":"MOGAMI GUN MOGAMI MACHI","大字町丁目コード":"063620001000","大字町丁目名":"大字大堀","緯度":38.755286,"経度":140.417435},{"都道府県コード":"06","都道府県名":"山形県","都道府県名カナ":"ヤマガタケン","都道府県名ローマ字":"YAMAGATA KEN","市区町村コード":"06362","市区町村名":"最上郡最上町","市区町村名カナ":"モガミグンモガミマチ","市区町村名ローマ字":"MOGAMI GUN MOGAMI MACHI","大字町丁目コード":"063620002000","大字町丁目名":"大字黒澤","緯度":38.776503,"経度":140.538224},{"都道府県コード":"06","都道府県名":"山形県","都道府県名カナ":"ヤマガタケン","都道府県名ローマ字":"YAMAGATA KEN","市区町村コード":"06362","市区町村名":"最上郡最上町","市区町村名カナ":"モガミグンモガミマチ","市区町村名ローマ字":"MOGAMI GUN MOGAMI MACHI","大字町丁目コード":"063620003000","大字町丁目名":"大字堺田","緯度":38.741907,"経度":140.612044},{"都道府県コード":"06","都道府県名":"山形県","都道府県名カナ":"ヤマガタケン","都道府県名ローマ字":"YAMAGATA KEN","市区町村コード":"06362","市区町村名":"最上郡最上町","市区町村名カナ":"モガミグンモガミマチ","市区町村名ローマ字":"MOGAMI GUN MOGAMI MACHI","大字町丁目コード":"063620004000","大字町丁目名":"大字志茂","緯度":38.784232,"経度":140.464521},{"都道府県コード":"06","都道府県名":"山形県","都道府県名カナ":"ヤマガタケン","都道府県名ローマ字":"YAMAGATA KEN","市区町村コード":"06362","市区町村名":"最上郡最上町","市区町村名カナ":"モガミグンモガミマチ","市区町村名ローマ字":"MOGAMI GUN MOGAMI MACHI","大字町丁目コード":"063620005000","大字町丁目名":"大字月楯","緯度":38.735013,"経度":140.494084},{"都道府県コード":"06","都道府県名":"山形県","都道府県名カナ":"ヤマガタケン","都道府県名ローマ字":"YAMAGATA KEN","市区町村コード":"06362","市区町村名":"最上郡最上町","市区町村名カナ":"モガミグンモガミマチ","市区町村名ローマ字":"MOGAMI GUN MOGAMI MACHI","大字町丁目コード":"063620006000","大字町丁目名":"大字富澤","緯度":38.724318,"経度":140.558887},{"都道府県コード":"06","都道府県名":"山形県","都道府県名カナ":"ヤマガタケン","都道府県名ローマ字":"YAMAGATA KEN","市区町村コード":"06362","市区町村名":"最上郡最上町","市区町村名カナ":"モガミグンモガミマチ","市区町村名ローマ字":"MOGAMI GUN MOGAMI MACHI","大字町丁目コード":"063620007000","大字町丁目名":"大字東法田","緯度":38.799271,"経度":140.512885},{"都道府県コード":"06","都道府県名":"山形県","都道府県名カナ":"ヤマガタケン","都道府県名ローマ字":"YAMAGATA KEN","市区町村コード":"06362","市区町村名":"最上郡最上町","市区町村名カナ":"モガミグンモガミマチ","市区町村名ローマ字":"MOGAMI GUN MOGAMI MACHI","大字町丁目コード":"063620008000","大字町丁目名":"大字法田","緯度":38.797332,"経度":140.490571},{"都道府県コード":"06","都道府県名":"山形県","都道府県名カナ":"ヤマガタケン","都道府県名ローマ字":"YAMAGATA KEN","市区町村コード":"06362","市区町村名":"最上郡最上町","市区町村名カナ":"モガミグンモガミマチ","市区町村名ローマ字":"MOGAMI GUN MOGAMI MACHI","大字町丁目コード":"063620009000","大字町丁目名":"大字本城","緯度":38.748285,"経度":140.531231},{"都道府県コード":"06","都道府県名":"山形県","都道府県名カナ":"ヤマガタケン","都道府県名ローマ字":"YAMAGATA KEN","市区町村コード":"06362","市区町村名":"最上郡最上町","市区町村名カナ":"モガミグンモガミマチ","市区町村名ローマ字":"MOGAMI GUN MOGAMI MACHI","大字町丁目コード":"063620010000","大字町丁目名":"大字満澤","緯度":38.725584,"経度":140.515096},{"都道府県コード":"06","都道府県名":"山形県","都道府県名カナ":"ヤマガタケン","都道府県名ローマ字":"YAMAGATA KEN","市区町村コード":"06362","市区町村名":"最上郡最上町","市区町村名カナ":"モガミグンモガミマチ","市区町村名ローマ字":"MOGAMI GUN MOGAMI MACHI","大字町丁目コード":"063620011000","大字町丁目名":"大字向町","緯度":38.779783,"経度":140.522085},{"都道府県コード":"06","都道府県名":"山形県","都道府県名カナ":"ヤマガタケン","都道府県名ローマ字":"YAMAGATA KEN","市区町村コード":"06362","市区町村名":"最上郡最上町","市区町村名カナ":"モガミグンモガミマチ","市区町村名ローマ字":"MOGAMI GUN MOGAMI MACHI","大字町丁目コード":"063620012000","大字町丁目名":"大字若宮","緯度":38.767029,"経度":140.49376}]