[{"都道府県コード":"19","都道府県名":"山梨県","都道府県名カナ":"ヤマナシケン","都道府県名ローマ字":"YAMANASHI KEN","市区町村コード":"19346","市区町村名":"西八代郡市川三郷町","市区町村名カナ":"ニシヤツシログンイチカワミサトチョウ","市区町村名ローマ字":"NISHIYATSUSHIRO GUN ICHIKAWAMISATO","大字町丁目コード":"193460001000","大字町丁目名":"岩下","緯度":35.492897,"経度":138.483474},{"都道府県コード":"19","都道府県名":"山梨県","都道府県名カナ":"ヤマナシケン","都道府県名ローマ字":"YAMANASHI KEN","市区町村コード":"19346","市区町村名":"西八代郡市川三郷町","市区町村名カナ":"ニシヤツシログンイチカワミサトチョウ","市区町村名ローマ字":"NISHIYATSUSHIRO GUN ICHIKAWAMISATO","大字町丁目コード":"193460002000","大字町丁目名":"寺所","緯度":35.501319,"経度":138.494369},{"都道府県コード":"19","都道府県名":"山梨県","都道府県名カナ":"ヤマナシケン","都道府県名ローマ字":"YAMANASHI KEN","市区町村コード":"19346","市区町村名":"西八代郡市川三郷町","市区町村名カナ":"ニシヤツシログンイチカワミサトチョウ","市区町村名ローマ字":"NISHIYATSUSHIRO GUN ICHIKAWAMISATO","大字町丁目コード":"193460003000","大字町丁目名":"五八","緯度":35.501272,"経度":138.484989},{"都道府県コード":"19","都道府県名":"山梨県","都道府県名カナ":"ヤマナシケン","都道府県名ローマ字":"YAMANASHI KEN","市区町村コード":"19346","市区町村名":"西八代郡市川三郷町","市区町村名カナ":"ニシヤツシログンイチカワミサトチョウ","市区町村名ローマ字":"NISHIYATSUSHIRO GUN ICHIKAWAMISATO","大字町丁目コード":"193460004000","大字町丁目名":"落居","緯度":35.509299,"経度":138.481345},{"都道府県コード":"19","都道府県名":"山梨県","都道府県名カナ":"ヤマナシケン","都道府県名ローマ字":"YAMANASHI KEN","市区町村コード":"19346","市区町村名":"西八代郡市川三郷町","市区町村名カナ":"ニシヤツシログンイチカワミサトチョウ","市区町村名ローマ字":"NISHIYATSUSHIRO GUN ICHIKAWAMISATO","大字町丁目コード":"193460005000","大字町丁目名":"葛篭沢","緯度":35.496541,"経度":138.472115},{"都道府県コード":"19","都道府県名":"山梨県","都道府県名カナ":"ヤマナシケン","都道府県名ローマ字":"YAMANASHI KEN","市区町村コード":"19346","市区町村名":"西八代郡市川三郷町","市区町村名カナ":"ニシヤツシログンイチカワミサトチョウ","市区町村名ローマ字":"NISHIYATSUSHIRO GUN ICHIKAWAMISATO","大字町丁目コード":"193460006000","大字町丁目名":"岩間","緯度":35.495555,"経度":138.45991},{"都道府県コード":"19","都道府県名":"山梨県","都道府県名カナ":"ヤマナシケン","都道府県名ローマ字":"YAMANASHI KEN","市区町村コード":"19346","市区町村名":"西八代郡市川三郷町","市区町村名カナ":"ニシヤツシログンイチカワミサトチョウ","市区町村名ローマ字":"NISHIYATSUSHIRO GUN ICHIKAWAMISATO","大字町丁目コード":"193460007000","大字町丁目名":"市川大門","緯度":35.55618,"経度":138.505189},{"都道府県コード":"19","都道府県名":"山梨県","都道府県名カナ":"ヤマナシケン","都道府県名ローマ字":"YAMANASHI KEN","市区町村コード":"19346","市区町村名":"西八代郡市川三郷町","市区町村名カナ":"ニシヤツシログンイチカワミサトチョウ","市区町村名ローマ字":"NISHIYATSUSHIRO GUN ICHIKAWAMISATO","大字町丁目コード":"193460008000","大字町丁目名":"高田","緯度":35.558261,"経度":138.486795},{"都道府県コード":"19","都道府県名":"山梨県","都道府県名カナ":"ヤマナシケン","都道府県名ローマ字":"YAMANASHI KEN","市区町村コード":"19346","市区町村名":"西八代郡市川三郷町","市区町村名カナ":"ニシヤツシログンイチカワミサトチョウ","市区町村名ローマ字":"NISHIYATSUSHIRO GUN ICHIKAWAMISATO","大字町丁目コード":"193460009000","大字町丁目名":"山保","緯度":35.528769,"経度":138.509539},{"都道府県コード":"19","都道府県名":"山梨県","都道府県名カナ":"ヤマナシケン","都道府県名ローマ字":"YAMANASHI KEN","市区町村コード":"19346","市区町村名":"西八代郡市川三郷町","市区町村名カナ":"ニシヤツシログンイチカワミサトチョウ","市区町村名ローマ字":"NISHIYATSUSHIRO GUN ICHIKAWAMISATO","大字町丁目コード":"193460010000","大字町丁目名":"印沢","緯度":35.55193,"経度":138.496026},{"都道府県コード":"19","都道府県名":"山梨県","都道府県名カナ":"ヤマナシケン","都道府県名ローマ字":"YAMANASHI KEN","市区町村コード":"19346","市区町村名":"西八代郡市川三郷町","市区町村名カナ":"ニシヤツシログンイチカワミサトチョウ","市区町村名ローマ字":"NISHIYATSUSHIRO GUN ICHIKAWAMISATO","大字町丁目コード":"193460011000","大字町丁目名":"楠甫","緯度":35.499752,"経度":138.451456},{"都道府県コード":"19","都道府県名":"山梨県","都道府県名カナ":"ヤマナシケン","都道府県名ローマ字":"YAMANASHI KEN","市区町村コード":"19346","市区町村名":"西八代郡市川三郷町","市区町村名カナ":"ニシヤツシログンイチカワミサトチョウ","市区町村名ローマ字":"NISHIYATSUSHIRO GUN ICHIKAWAMISATO","大字町丁目コード":"193460012000","大字町丁目名":"宮原","緯度":35.487477,"経度":138.4707},{"都道府県コード":"19","都道府県名":"山梨県","都道府県名カナ":"ヤマナシケン","都道府県名ローマ字":"YAMANASHI KEN","市区町村コード":"19346","市区町村名":"西八代郡市川三郷町","市区町村名カナ":"ニシヤツシログンイチカワミサトチョウ","市区町村名ローマ字":"NISHIYATSUSHIRO GUN ICHIKAWAMISATO","大字町丁目コード":"193460013000","大字町丁目名":"鴨狩津向","緯度":35.476686,"経度":138.451851},{"都道府県コード":"19","都道府県名":"山梨県","都道府県名カナ":"ヤマナシケン","都道府県名ローマ字":"YAMANASHI KEN","市区町村コード":"19346","市区町村名":"西八代郡市川三郷町","市区町村名カナ":"ニシヤツシログンイチカワミサトチョウ","市区町村名ローマ字":"NISHIYATSUSHIRO GUN ICHIKAWAMISATO","大字町丁目コード":"193460014000","大字町丁目名":"三帳","緯度":35.531626,"経度":138.57481},{"都道府県コード":"19","都道府県名":"山梨県","都道府県名カナ":"ヤマナシケン","都道府県名ローマ字":"YAMANASHI KEN","市区町村コード":"19346","市区町村名":"西八代郡市川三郷町","市区町村名カナ":"ニシヤツシログンイチカワミサトチョウ","市区町村名ローマ字":"NISHIYATSUSHIRO GUN ICHIKAWAMISATO","大字町丁目コード":"193460015000","大字町丁目名":"垈","緯度":35.529352,"経度":138.537529},{"都道府県コード":"19","都道府県名":"山梨県","都道府県名カナ":"ヤマナシケン","都道府県名ローマ字":"YAMANASHI KEN","市区町村コード":"19346","市区町村名":"西八代郡市川三郷町","市区町村名カナ":"ニシヤツシログンイチカワミサトチョウ","市区町村名ローマ字":"NISHIYATSUSHIRO GUN ICHIKAWAMISATO","大字町丁目コード":"193460016000","大字町丁目名":"高萩","緯度":35.528551,"経度":138.558034},{"都道府県コード":"19","都道府県名":"山梨県","都道府県名カナ":"ヤマナシケン","都道府県名ローマ字":"YAMANASHI KEN","市区町村コード":"19346","市区町村名":"西八代郡市川三郷町","市区町村名カナ":"ニシヤツシログンイチカワミサトチョウ","市区町村名ローマ字":"NISHIYATSUSHIRO GUN ICHIKAWAMISATO","大字町丁目コード":"193460017000","大字町丁目名":"畑熊","緯度":35.540562,"経度":138.536229},{"都道府県コード":"19","都道府県名":"山梨県","都道府県名カナ":"ヤマナシケン","都道府県名ローマ字":"YAMANASHI KEN","市区町村コード":"19346","市区町村名":"西八代郡市川三郷町","市区町村名カナ":"ニシヤツシログンイチカワミサトチョウ","市区町村名ローマ字":"NISHIYATSUSHIRO GUN ICHIKAWAMISATO","大字町丁目コード":"193460018000","大字町丁目名":"中山","緯度":35.545819,"経度":138.554307},{"都道府県コード":"19","都道府県名":"山梨県","都道府県名カナ":"ヤマナシケン","都道府県名ローマ字":"YAMANASHI KEN","市区町村コード":"19346","市区町村名":"西八代郡市川三郷町","市区町村名カナ":"ニシヤツシログンイチカワミサトチョウ","市区町村名ローマ字":"NISHIYATSUSHIRO GUN ICHIKAWAMISATO","大字町丁目コード":"193460019000","大字町丁目名":"下芦川","緯度":35.534363,"経度":138.58465},{"都道府県コード":"19","都道府県名":"山梨県","都道府県名カナ":"ヤマナシケン","都道府県名ローマ字":"YAMANASHI KEN","市区町村コード":"19346","市区町村名":"西八代郡市川三郷町","市区町村名カナ":"ニシヤツシログンイチカワミサトチョウ","市区町村名ローマ字":"NISHIYATSUSHIRO GUN ICHIKAWAMISATO","大字町丁目コード":"193460020000","大字町丁目名":"大塚","緯度":35.568788,"経度":138.534481},{"都道府県コード":"19","都道府県名":"山梨県","都道府県名カナ":"ヤマナシケン","都道府県名ローマ字":"YAMANASHI KEN","市区町村コード":"19346","市区町村名":"西八代郡市川三郷町","市区町村名カナ":"ニシヤツシログンイチカワミサトチョウ","市区町村名ローマ字":"NISHIYATSUSHIRO GUN ICHIKAWAMISATO","大字町丁目コード":"193460021000","大字町丁目名":"上野","緯度":35.560442,"経度":138.521998},{"都道府県コード":"19","都道府県名":"山梨県","都道府県名カナ":"ヤマナシケン","都道府県名ローマ字":"YAMANASHI KEN","市区町村コード":"19346","市区町村名":"西八代郡市川三郷町","市区町村名カナ":"ニシヤツシログンイチカワミサトチョウ","市区町村名ローマ字":"NISHIYATSUSHIRO GUN ICHIKAWAMISATO","大字町丁目コード":"193460022000","大字町丁目名":"八之尻","緯度":35.536472,"経度":138.483765},{"都道府県コード":"19","都道府県名":"山梨県","都道府県名カナ":"ヤマナシケン","都道府県名ローマ字":"YAMANASHI KEN","市区町村コード":"19346","市区町村名":"西八代郡市川三郷町","市区町村名カナ":"ニシヤツシログンイチカワミサトチョウ","市区町村名ローマ字":"NISHIYATSUSHIRO GUN ICHIKAWAMISATO","大字町丁目コード":"193460023000","大字町丁目名":"下大鳥居","緯度":35.549081,"経度":138.479605},{"都道府県コード":"19","都道府県名":"山梨県","都道府県名カナ":"ヤマナシケン","都道府県名ローマ字":"YAMANASHI KEN","市区町村コード":"19346","市区町村名":"西八代郡市川三郷町","市区町村名カナ":"ニシヤツシログンイチカワミサトチョウ","市区町村名ローマ字":"NISHIYATSUSHIRO GUN ICHIKAWAMISATO","大字町丁目コード":"193460024000","大字町丁目名":"黒沢","緯度":35.53178,"経度":138.466725}]